{
  "script": "13_detect_foam_nir.py",
  "run_id": "03f9858851f3",
  "generated_at_utc": "2026-03-27T13:40:52.843094+00:00",
  "code_version": "b7f2437",
  "config": {
    "spot": "Minutes",
    "slug": "minutes",
    "bbox": [
      -63.4303,
      44.6222,
      -63.4003,
      44.6422
    ],
    "point": {
      "lat": 44.6322,
      "lon": -63.4153
    }
  },
  "parameters": {
    "nir_foam_threshold": 800,
    "buffer_distance_m": 200,
    "pixel_size_m": 10,
    "max_cloud_percent": 15.0,
    "min_date": "2021-10-01"
  },
  "summary": {
    "scenes_processed": 120,
    "segments_processed": 1,
    "total_detections": 120,
    "errors": 0,
    "scenes_with_foam": 110,
    "date_range": {
      "start": "2021-10-07",
      "end": "2026-03-18"
    },
    "quality": {
      "scenes_high_quality": 116,
      "scenes_usable": 120,
      "scenes_discarded": 0,
      "mean_quality_score": 97.7
    }
  },
  "scene_quality": [
    {
      "date": "2021-10-07",
      "cloud_pct": 0.01,
      "shadow_pct": 0.0,
      "snow_land_pct": 0.0,
      "valid_pct": 100.04,
      "quality_score": 100.0
    },
    {
      "date": "2021-10-10",
      "cloud_pct": 0.0,
      "shadow_pct": 0.0,
      "snow_land_pct": 0.0,
      "valid_pct": 100.04,
      "quality_score": 100.0
    },
    {
      "date": "2021-11-04",
      "cloud_pct": 0.03,
      "shadow_pct": 0.0,
      "snow_land_pct": 0.0,
      "valid_pct": 100.04,
      "quality_score": 100.0
    },
    {
      "date": "2021-11-06",
      "cloud_pct": 0.0,
      "shadow_pct": 0.0,
      "snow_land_pct": 0.24,
      "valid_pct": 100.04,
      "quality_score": 100.0
    },
    {
      "date": "2021-11-09",
      "cloud_pct": 0.0,
      "shadow_pct": 0.0,
      "snow_land_pct": 0.09,
      "valid_pct": 100.04,
      "quality_score": 100.0
    },
    {
      "date": "2021-11-11",
      "cloud_pct": 0.11,
      "shadow_pct": 0.0,
      "snow_land_pct": 0.0,
      "valid_pct": 100.04,
      "quality_score": 100.0
    },
    {
      "date": "2021-12-04",
      "cloud_pct": 0.02,
      "shadow_pct": 2.03,
      "snow_land_pct": 0.79,
      "valid_pct": 100.04,
      "quality_score": 99.6
    },
    {
      "date": "2021-12-24",
      "cloud_pct": 3.0,
      "shadow_pct": 0.0,
      "snow_land_pct": 0.1,
      "valid_pct": 100.04,
      "quality_score": 98.8
    },
    {
      "date": "2022-02-12",
      "cloud_pct": 3.4,
      "shadow_pct": 0.0,
      "snow_land_pct": 0.0,
      "valid_pct": 100.04,
      "quality_score": 98.6
    },
    {
      "date": "2022-02-24",
      "cloud_pct": 0.88,
      "shadow_pct": 0.0,
      "snow_land_pct": 0.0,
      "valid_pct": 100.04,
      "quality_score": 99.6
    },
    {
      "date": "2022-03-11",
      "cloud_pct": 0.46,
      "shadow_pct": 0.0,
      "snow_land_pct": 0.04,
      "valid_pct": 100.04,
      "quality_score": 99.8
    },
    {
      "date": "2022-04-05",
      "cloud_pct": 1.58,
      "shadow_pct": 0.0,
      "snow_land_pct": 0.0,
      "valid_pct": 100.04,
      "quality_score": 99.4
    },
    {
      "date": "2022-04-18",
      "cloud_pct": 0.1,
      "shadow_pct": 0.0,
      "snow_land_pct": 0.0,
      "valid_pct": 100.04,
      "quality_score": 100.0
    },
    {
      "date": "2022-05-10",
      "cloud_pct": 1.98,
      "shadow_pct": 0.0,
      "snow_land_pct": 2.69,
      "valid_pct": 100.04,
      "quality_score": 98.7
    },
    {
      "date": "2022-05-25",
      "cloud_pct": 0.14,
      "shadow_pct": 0.0,
      "snow_land_pct": 0.0,
      "valid_pct": 100.04,
      "quality_score": 99.9
    },
    {
      "date": "2022-06-07",
      "cloud_pct": 0.1,
      "shadow_pct": 0.0,
      "snow_land_pct": 0.0,
      "valid_pct": 100.04,
      "quality_score": 100.0
    },
    {
      "date": "2022-06-12",
      "cloud_pct": 7.49,
      "shadow_pct": 0.02,
      "snow_land_pct": 0.0,
      "valid_pct": 100.04,
      "quality_score": 97.0
    },
    {
      "date": "2022-06-19",
      "cloud_pct": 0.3,
      "shadow_pct": 1.51,
      "snow_land_pct": 0.5,
      "valid_pct": 100.04,
      "quality_score": 99.6
    },
    {
      "date": "2022-07-04",
      "cloud_pct": 0.0,
      "shadow_pct": 0.0,
      "snow_land_pct": 0.0,
      "valid_pct": 100.04,
      "quality_score": 100.0
    },
    {
      "date": "2022-07-07",
      "cloud_pct": 3.08,
      "shadow_pct": 4.44,
      "snow_land_pct": 0.0,
      "valid_pct": 100.04,
      "quality_score": 98.3
    },
    {
      "date": "2022-07-09",
      "cloud_pct": 0.07,
      "shadow_pct": 0.0,
      "snow_land_pct": 0.0,
      "valid_pct": 100.04,
      "quality_score": 100.0
    },
    {
      "date": "2022-07-12",
      "cloud_pct": 0.11,
      "shadow_pct": 0.0,
      "snow_land_pct": 0.0,
      "valid_pct": 100.04,
      "quality_score": 100.0
    },
    {
      "date": "2022-08-21",
      "cloud_pct": 0.0,
      "shadow_pct": 0.0,
      "snow_land_pct": 0.0,
      "valid_pct": 100.04,
      "quality_score": 100.0
    },
    {
      "date": "2022-08-28",
      "cloud_pct": 0.0,
      "shadow_pct": 0.0,
      "snow_land_pct": 0.0,
      "valid_pct": 100.04,
      "quality_score": 100.0
    },
    {
      "date": "2022-09-02",
      "cloud_pct": 17.13,
      "shadow_pct": 15.25,
      "snow_land_pct": 0.0,
      "valid_pct": 100.04,
      "quality_score": 91.6
    },
    {
      "date": "2022-09-07",
      "cloud_pct": 55.4,
      "shadow_pct": 18.97,
      "snow_land_pct": 0.0,
      "valid_pct": 100.04,
      "quality_score": 75.9
    },
    {
      "date": "2022-09-10",
      "cloud_pct": 0.76,
      "shadow_pct": 0.3,
      "snow_land_pct": 1.05,
      "valid_pct": 100.04,
      "quality_score": 99.5
    },
    {
      "date": "2022-09-17",
      "cloud_pct": 0.08,
      "shadow_pct": 0.0,
      "snow_land_pct": 0.0,
      "valid_pct": 100.04,
      "quality_score": 100.0
    },
    {
      "date": "2022-09-25",
      "cloud_pct": 0.01,
      "shadow_pct": 0.0,
      "snow_land_pct": 0.0,
      "valid_pct": 100.04,
      "quality_score": 100.0
    },
    {
      "date": "2022-09-30",
      "cloud_pct": 0.45,
      "shadow_pct": 0.0,
      "snow_land_pct": 0.0,
      "valid_pct": 100.04,
      "quality_score": 99.8
    },
    {
      "date": "2022-10-12",
      "cloud_pct": 0.08,
      "shadow_pct": 0.0,
      "snow_land_pct": 0.0,
      "valid_pct": 100.04,
      "quality_score": 100.0
    },
    {
      "date": "2022-10-30",
      "cloud_pct": 0.01,
      "shadow_pct": 0.0,
      "snow_land_pct": 0.0,
      "valid_pct": 100.04,
      "quality_score": 100.0
    },
    {
      "date": "2022-11-09",
      "cloud_pct": 0.0,
      "shadow_pct": 0.0,
      "snow_land_pct": 0.0,
      "valid_pct": 100.04,
      "quality_score": 100.0
    },
    {
      "date": "2022-11-21",
      "cloud_pct": 0.05,
      "shadow_pct": 0.0,
      "snow_land_pct": 0.02,
      "valid_pct": 100.04,
      "quality_score": 100.0
    },
    {
      "date": "2022-11-24",
      "cloud_pct": 0.99,
      "shadow_pct": 0.0,
      "snow_land_pct": 0.0,
      "valid_pct": 100.04,
      "quality_score": 99.6
    },
    {
      "date": "2022-11-29",
      "cloud_pct": 0.05,
      "shadow_pct": 0.0,
      "snow_land_pct": 0.21,
      "valid_pct": 100.04,
      "quality_score": 99.9
    },
    {
      "date": "2023-01-25",
      "cloud_pct": 0.47,
      "shadow_pct": 0.0,
      "snow_land_pct": 0.5,
      "valid_pct": 100.04,
      "quality_score": 99.7
    },
    {
      "date": "2023-02-09",
      "cloud_pct": 0.94,
      "shadow_pct": 0.0,
      "snow_land_pct": 0.0,
      "valid_pct": 100.04,
      "quality_score": 99.6
    },
    {
      "date": "2023-02-22",
      "cloud_pct": 0.05,
      "shadow_pct": 0.0,
      "snow_land_pct": 0.98,
      "valid_pct": 100.04,
      "quality_score": 99.8
    },
    {
      "date": "2023-03-11",
      "cloud_pct": 0.02,
      "shadow_pct": 0.0,
      "snow_land_pct": 76.93,
      "valid_pct": 100.04,
      "quality_score": 84.6
    },
    {
      "date": "2023-03-19",
      "cloud_pct": 0.02,
      "shadow_pct": 0.0,
      "snow_land_pct": 2.59,
      "valid_pct": 100.04,
      "quality_score": 99.5
    },
    {
      "date": "2023-03-21",
      "cloud_pct": 0.0,
      "shadow_pct": 0.0,
      "snow_land_pct": 0.0,
      "valid_pct": 100.04,
      "quality_score": 100.0
    },
    {
      "date": "2023-04-08",
      "cloud_pct": 1.04,
      "shadow_pct": 0.0,
      "snow_land_pct": 0.0,
      "valid_pct": 100.04,
      "quality_score": 99.6
    },
    {
      "date": "2023-04-10",
      "cloud_pct": 0.06,
      "shadow_pct": 0.0,
      "snow_land_pct": 0.0,
      "valid_pct": 100.04,
      "quality_score": 100.0
    },
    {
      "date": "2023-04-13",
      "cloud_pct": 0.0,
      "shadow_pct": 0.0,
      "snow_land_pct": 0.0,
      "valid_pct": 100.04,
      "quality_score": 100.0
    },
    {
      "date": "2023-04-28",
      "cloud_pct": 0.08,
      "shadow_pct": 0.0,
      "snow_land_pct": 0.0,
      "valid_pct": 100.04,
      "quality_score": 100.0
    },
    {
      "date": "2023-05-23",
      "cloud_pct": 0.06,
      "shadow_pct": 0.0,
      "snow_land_pct": 0.0,
      "valid_pct": 100.04,
      "quality_score": 100.0
    },
    {
      "date": "2023-05-28",
      "cloud_pct": 0.06,
      "shadow_pct": 0.0,
      "snow_land_pct": 0.0,
      "valid_pct": 100.04,
      "quality_score": 100.0
    },
    {
      "date": "2023-05-30",
      "cloud_pct": 0.17,
      "shadow_pct": 0.0,
      "snow_land_pct": 0.0,
      "valid_pct": 100.04,
      "quality_score": 99.9
    },
    {
      "date": "2023-06-22",
      "cloud_pct": 0.02,
      "shadow_pct": 0.0,
      "snow_land_pct": 0.0,
      "valid_pct": 100.04,
      "quality_score": 100.0
    },
    {
      "date": "2023-07-14",
      "cloud_pct": 0.07,
      "shadow_pct": 0.0,
      "snow_land_pct": 0.0,
      "valid_pct": 100.04,
      "quality_score": 100.0
    },
    {
      "date": "2023-08-03",
      "cloud_pct": 0.0,
      "shadow_pct": 0.0,
      "snow_land_pct": 0.0,
      "valid_pct": 100.04,
      "quality_score": 100.0
    },
    {
      "date": "2023-08-23",
      "cloud_pct": 0.0,
      "shadow_pct": 0.52,
      "snow_land_pct": 0.0,
      "valid_pct": 100.04,
      "quality_score": 99.9
    },
    {
      "date": "2023-08-28",
      "cloud_pct": 19.03,
      "shadow_pct": 14.77,
      "snow_land_pct": 0.0,
      "valid_pct": 100.04,
      "quality_score": 90.9
    },
    {
      "date": "2023-09-02",
      "cloud_pct": 0.0,
      "shadow_pct": 0.0,
      "snow_land_pct": 0.0,
      "valid_pct": 100.04,
      "quality_score": 100.0
    },
    {
      "date": "2023-09-27",
      "cloud_pct": 49.93,
      "shadow_pct": 0.0,
      "snow_land_pct": 6.27,
      "valid_pct": 100.04,
      "quality_score": 78.8
    },
    {
      "date": "2023-10-02",
      "cloud_pct": 0.02,
      "shadow_pct": 0.0,
      "snow_land_pct": 0.02,
      "valid_pct": 100.04,
      "quality_score": 100.0
    },
    {
      "date": "2023-10-10",
      "cloud_pct": 0.0,
      "shadow_pct": 0.0,
      "snow_land_pct": 0.52,
      "valid_pct": 100.04,
      "quality_score": 99.9
    },
    {
      "date": "2023-10-12",
      "cloud_pct": 0.0,
      "shadow_pct": 0.0,
      "snow_land_pct": 0.0,
      "valid_pct": 100.04,
      "quality_score": 100.0
    },
    {
      "date": "2023-11-19",
      "cloud_pct": 1.2,
      "shadow_pct": 0.0,
      "snow_land_pct": 13.06,
      "valid_pct": 100.04,
      "quality_score": 96.9
    },
    {
      "date": "2023-11-21",
      "cloud_pct": 0.27,
      "shadow_pct": 0.0,
      "snow_land_pct": 0.0,
      "valid_pct": 100.04,
      "quality_score": 99.9
    },
    {
      "date": "2023-12-09",
      "cloud_pct": 0.0,
      "shadow_pct": 0.0,
      "snow_land_pct": 86.21,
      "valid_pct": 100.04,
      "quality_score": 82.8
    },
    {
      "date": "2024-03-20",
      "cloud_pct": 0.0,
      "shadow_pct": 0.0,
      "snow_land_pct": 0.02,
      "valid_pct": 100.04,
      "quality_score": 100.0
    },
    {
      "date": "2024-04-02",
      "cloud_pct": 0.05,
      "shadow_pct": 0.0,
      "snow_land_pct": 0.0,
      "valid_pct": 100.04,
      "quality_score": 100.0
    },
    {
      "date": "2024-04-27",
      "cloud_pct": 0.03,
      "shadow_pct": 0.0,
      "snow_land_pct": 0.0,
      "valid_pct": 100.04,
      "quality_score": 100.0
    },
    {
      "date": "2024-05-14",
      "cloud_pct": 0.0,
      "shadow_pct": 0.0,
      "snow_land_pct": 0.0,
      "valid_pct": 100.04,
      "quality_score": 100.0
    },
    {
      "date": "2024-05-29",
      "cloud_pct": 0.32,
      "shadow_pct": 0.31,
      "snow_land_pct": 0.19,
      "valid_pct": 100.04,
      "quality_score": 99.8
    },
    {
      "date": "2024-06-16",
      "cloud_pct": 0.26,
      "shadow_pct": 0.0,
      "snow_land_pct": 0.0,
      "valid_pct": 100.04,
      "quality_score": 99.9
    },
    {
      "date": "2024-06-21",
      "cloud_pct": 0.11,
      "shadow_pct": 0.0,
      "snow_land_pct": 0.0,
      "valid_pct": 100.04,
      "quality_score": 100.0
    },
    {
      "date": "2024-06-28",
      "cloud_pct": 0.13,
      "shadow_pct": 0.0,
      "snow_land_pct": 0.0,
      "valid_pct": 100.04,
      "quality_score": 99.9
    },
    {
      "date": "2024-07-03",
      "cloud_pct": 0.02,
      "shadow_pct": 0.0,
      "snow_land_pct": 0.0,
      "valid_pct": 100.04,
      "quality_score": 100.0
    },
    {
      "date": "2024-07-28",
      "cloud_pct": 0.02,
      "shadow_pct": 0.0,
      "snow_land_pct": 0.0,
      "valid_pct": 100.04,
      "quality_score": 100.0
    },
    {
      "date": "2024-08-12",
      "cloud_pct": 0.02,
      "shadow_pct": 0.0,
      "snow_land_pct": 0.0,
      "valid_pct": 100.04,
      "quality_score": 100.0
    },
    {
      "date": "2024-08-22",
      "cloud_pct": 12.64,
      "shadow_pct": 4.61,
      "snow_land_pct": 0.0,
      "valid_pct": 100.04,
      "quality_score": 94.5
    },
    {
      "date": "2024-08-25",
      "cloud_pct": 0.01,
      "shadow_pct": 0.0,
      "snow_land_pct": 0.0,
      "valid_pct": 100.04,
      "quality_score": 100.0
    },
    {
      "date": "2024-08-30",
      "cloud_pct": 0.0,
      "shadow_pct": 0.0,
      "snow_land_pct": 0.0,
      "valid_pct": 100.04,
      "quality_score": 100.0
    },
    {
      "date": "2024-09-04",
      "cloud_pct": 0.05,
      "shadow_pct": 0.0,
      "snow_land_pct": 0.0,
      "valid_pct": 100.04,
      "quality_score": 100.0
    },
    {
      "date": "2024-09-11",
      "cloud_pct": 50.15,
      "shadow_pct": 15.41,
      "snow_land_pct": 0.0,
      "valid_pct": 100.04,
      "quality_score": 78.4
    },
    {
      "date": "2024-09-14",
      "cloud_pct": 0.05,
      "shadow_pct": 0.0,
      "snow_land_pct": 0.0,
      "valid_pct": 100.04,
      "quality_score": 100.0
    },
    {
      "date": "2024-09-16",
      "cloud_pct": 0.0,
      "shadow_pct": 0.0,
      "snow_land_pct": 0.0,
      "valid_pct": 100.04,
      "quality_score": 100.0
    },
    {
      "date": "2024-10-19",
      "cloud_pct": 0.0,
      "shadow_pct": 0.0,
      "snow_land_pct": 0.0,
      "valid_pct": 100.04,
      "quality_score": 100.0
    },
    {
      "date": "2024-10-29",
      "cloud_pct": 0.06,
      "shadow_pct": 0.0,
      "snow_land_pct": 0.0,
      "valid_pct": 100.04,
      "quality_score": 100.0
    },
    {
      "date": "2024-11-10",
      "cloud_pct": 0.01,
      "shadow_pct": 0.0,
      "snow_land_pct": 0.0,
      "valid_pct": 100.04,
      "quality_score": 100.0
    },
    {
      "date": "2024-12-15",
      "cloud_pct": 3.16,
      "shadow_pct": 0.0,
      "snow_land_pct": 0.03,
      "valid_pct": 100.04,
      "quality_score": 98.7
    },
    {
      "date": "2025-03-03",
      "cloud_pct": 2.24,
      "shadow_pct": 0.0,
      "snow_land_pct": 51.33,
      "valid_pct": 100.04,
      "quality_score": 88.8
    },
    {
      "date": "2025-03-13",
      "cloud_pct": 0.9,
      "shadow_pct": 0.0,
      "snow_land_pct": 0.0,
      "valid_pct": 100.04,
      "quality_score": 99.6
    },
    {
      "date": "2025-03-15",
      "cloud_pct": 26.22,
      "shadow_pct": 0.0,
      "snow_land_pct": 0.13,
      "valid_pct": 100.04,
      "quality_score": 89.5
    },
    {
      "date": "2025-04-02",
      "cloud_pct": 3.55,
      "shadow_pct": 0.0,
      "snow_land_pct": 0.16,
      "valid_pct": 100.04,
      "quality_score": 98.6
    },
    {
      "date": "2025-05-14",
      "cloud_pct": 0.08,
      "shadow_pct": 0.0,
      "snow_land_pct": 0.0,
      "valid_pct": 100.04,
      "quality_score": 100.0
    },
    {
      "date": "2025-05-27",
      "cloud_pct": 0.05,
      "shadow_pct": 0.0,
      "snow_land_pct": 0.0,
      "valid_pct": 100.04,
      "quality_score": 100.0
    },
    {
      "date": "2025-06-11",
      "cloud_pct": 0.05,
      "shadow_pct": 0.0,
      "snow_land_pct": 0.0,
      "valid_pct": 100.04,
      "quality_score": 100.0
    },
    {
      "date": "2025-06-16",
      "cloud_pct": 0.5,
      "shadow_pct": 0.0,
      "snow_land_pct": 0.0,
      "valid_pct": 100.04,
      "quality_score": 99.8
    },
    {
      "date": "2025-06-21",
      "cloud_pct": 0.1,
      "shadow_pct": 0.0,
      "snow_land_pct": 0.0,
      "valid_pct": 100.04,
      "quality_score": 100.0
    },
    {
      "date": "2025-07-16",
      "cloud_pct": 0.0,
      "shadow_pct": 0.0,
      "snow_land_pct": 0.0,
      "valid_pct": 100.04,
      "quality_score": 100.0
    },
    {
      "date": "2025-07-23",
      "cloud_pct": 0.04,
      "shadow_pct": 0.0,
      "snow_land_pct": 0.0,
      "valid_pct": 100.04,
      "quality_score": 100.0
    },
    {
      "date": "2025-07-26",
      "cloud_pct": 0.0,
      "shadow_pct": 0.0,
      "snow_land_pct": 0.0,
      "valid_pct": 100.04,
      "quality_score": 100.0
    },
    {
      "date": "2025-07-28",
      "cloud_pct": 14.89,
      "shadow_pct": 0.0,
      "snow_land_pct": 0.0,
      "valid_pct": 100.04,
      "quality_score": 94.0
    },
    {
      "date": "2025-08-02",
      "cloud_pct": 0.11,
      "shadow_pct": 0.0,
      "snow_land_pct": 0.0,
      "valid_pct": 100.04,
      "quality_score": 100.0
    },
    {
      "date": "2025-08-12",
      "cloud_pct": 0.04,
      "shadow_pct": 0.0,
      "snow_land_pct": 0.0,
      "valid_pct": 100.04,
      "quality_score": 100.0
    },
    {
      "date": "2025-08-15",
      "cloud_pct": 0.03,
      "shadow_pct": 0.0,
      "snow_land_pct": 0.0,
      "valid_pct": 100.04,
      "quality_score": 100.0
    },
    {
      "date": "2025-08-17",
      "cloud_pct": 2.4,
      "shadow_pct": 0.0,
      "snow_land_pct": 0.0,
      "valid_pct": 100.04,
      "quality_score": 99.0
    },
    {
      "date": "2025-09-01",
      "cloud_pct": 5.58,
      "shadow_pct": 1.52,
      "snow_land_pct": 0.0,
      "valid_pct": 100.04,
      "quality_score": 97.6
    },
    {
      "date": "2025-09-04",
      "cloud_pct": 0.02,
      "shadow_pct": 0.0,
      "snow_land_pct": 0.0,
      "valid_pct": 100.04,
      "quality_score": 100.0
    },
    {
      "date": "2025-09-14",
      "cloud_pct": 82.12,
      "shadow_pct": 2.1,
      "snow_land_pct": 0.0,
      "valid_pct": 100.04,
      "quality_score": 66.9
    },
    {
      "date": "2025-09-16",
      "cloud_pct": 0.02,
      "shadow_pct": 0.0,
      "snow_land_pct": 0.0,
      "valid_pct": 100.04,
      "quality_score": 100.0
    },
    {
      "date": "2025-09-21",
      "cloud_pct": 0.06,
      "shadow_pct": 0.0,
      "snow_land_pct": 0.0,
      "valid_pct": 100.04,
      "quality_score": 100.0
    },
    {
      "date": "2025-09-29",
      "cloud_pct": 0.0,
      "shadow_pct": 0.0,
      "snow_land_pct": 0.0,
      "valid_pct": 100.04,
      "quality_score": 100.0
    },
    {
      "date": "2025-10-04",
      "cloud_pct": 0.0,
      "shadow_pct": 0.0,
      "snow_land_pct": 0.0,
      "valid_pct": 100.04,
      "quality_score": 100.0
    },
    {
      "date": "2025-10-24",
      "cloud_pct": 0.0,
      "shadow_pct": 0.0,
      "snow_land_pct": 0.04,
      "valid_pct": 100.04,
      "quality_score": 100.0
    },
    {
      "date": "2025-11-03",
      "cloud_pct": 0.0,
      "shadow_pct": 0.0,
      "snow_land_pct": 0.0,
      "valid_pct": 100.04,
      "quality_score": 100.0
    },
    {
      "date": "2025-11-05",
      "cloud_pct": 0.06,
      "shadow_pct": 0.0,
      "snow_land_pct": 0.0,
      "valid_pct": 100.04,
      "quality_score": 100.0
    },
    {
      "date": "2025-11-23",
      "cloud_pct": 0.0,
      "shadow_pct": 0.0,
      "snow_land_pct": 0.0,
      "valid_pct": 100.04,
      "quality_score": 100.0
    },
    {
      "date": "2025-12-05",
      "cloud_pct": 1.72,
      "shadow_pct": 0.91,
      "snow_land_pct": 0.0,
      "valid_pct": 100.04,
      "quality_score": 99.2
    },
    {
      "date": "2025-12-18",
      "cloud_pct": 0.05,
      "shadow_pct": 0.0,
      "snow_land_pct": 0.28,
      "valid_pct": 100.04,
      "quality_score": 99.9
    },
    {
      "date": "2025-12-23",
      "cloud_pct": 0.94,
      "shadow_pct": 0.0,
      "snow_land_pct": 0.0,
      "valid_pct": 100.04,
      "quality_score": 99.6
    },
    {
      "date": "2026-02-13",
      "cloud_pct": 6.61,
      "shadow_pct": 0.0,
      "snow_land_pct": 77.44,
      "valid_pct": 100.04,
      "quality_score": 81.9
    },
    {
      "date": "2026-02-28",
      "cloud_pct": 0.0,
      "shadow_pct": 0.0,
      "snow_land_pct": 87.26,
      "valid_pct": 100.04,
      "quality_score": 82.5
    },
    {
      "date": "2026-03-03",
      "cloud_pct": 0.0,
      "shadow_pct": 0.0,
      "snow_land_pct": 85.98,
      "valid_pct": 100.04,
      "quality_score": 82.8
    },
    {
      "date": "2026-03-10",
      "cloud_pct": 0.01,
      "shadow_pct": 0.0,
      "snow_land_pct": 71.29,
      "valid_pct": 100.04,
      "quality_score": 85.7
    },
    {
      "date": "2026-03-18",
      "cloud_pct": 7.57,
      "shadow_pct": 0.0,
      "snow_land_pct": 4.92,
      "valid_pct": 100.04,
      "quality_score": 96.0
    }
  ],
  "detections": [
    {
      "segment_id": "ns-seg-04002",
      "date": "2021-10-07",
      "swell_height_m": 0.38,
      "swell_period_s": 10.2,
      "swell_direction_deg": 138,
      "wave_height_m": 0.46,
      "cloud_pct": 0.01,
      "shadow_pct": 0.0,
      "snow_land_pct": 0.0,
      "valid_pct": 100.04,
      "quality_score": 100.0,
      "foam_fraction": 0.1766,
      "foam_extent_m": 87.3,
      "mean_nir": 342.8,
      "max_nir": 2786,
      "water_pixel_count": 988,
      "foam_pixel_count": 174.50980392156862,
      "total_buffer_pixels": 988
    },
    {
      "segment_id": "ns-seg-04002",
      "date": "2021-10-10",
      "swell_height_m": 0.28,
      "swell_period_s": 9.9,
      "swell_direction_deg": 137,
      "wave_height_m": 0.38,
      "cloud_pct": 0.0,
      "shadow_pct": 0.0,
      "snow_land_pct": 0.0,
      "valid_pct": 100.04,
      "quality_score": 100.0,
      "foam_fraction": 0.1141,
      "foam_extent_m": 56.8,
      "mean_nir": 255.4,
      "max_nir": 2990,
      "water_pixel_count": 996,
      "foam_pixel_count": 113.64313725490197,
      "total_buffer_pixels": 996
    },
    {
      "segment_id": "ns-seg-04002",
      "date": "2021-11-04",
      "swell_height_m": 0.56,
      "swell_period_s": 8.3,
      "swell_direction_deg": 104,
      "wave_height_m": 0.64,
      "cloud_pct": 0.03,
      "shadow_pct": 0.0,
      "snow_land_pct": 0.0,
      "valid_pct": 100.04,
      "quality_score": 100.0,
      "foam_fraction": 0.2638,
      "foam_extent_m": 129.3,
      "mean_nir": 490.3,
      "max_nir": 2652,
      "water_pixel_count": 980,
      "foam_pixel_count": 258.5607843137255,
      "total_buffer_pixels": 980
    },
    {
      "segment_id": "ns-seg-04002",
      "date": "2021-11-06",
      "swell_height_m": 0.98,
      "swell_period_s": 7.65,
      "swell_direction_deg": 117,
      "wave_height_m": 0.98,
      "cloud_pct": 0.0,
      "shadow_pct": 0.0,
      "snow_land_pct": 0.24,
      "valid_pct": 100.04,
      "quality_score": 100.0,
      "foam_fraction": 0.3014,
      "foam_extent_m": 154.9,
      "mean_nir": 569.7,
      "max_nir": 2566,
      "water_pixel_count": 1028,
      "foam_pixel_count": 309.89019607843136,
      "total_buffer_pixels": 1028
    },
    {
      "segment_id": "ns-seg-04002",
      "date": "2021-11-09",
      "swell_height_m": 1.04,
      "swell_period_s": 8.0,
      "swell_direction_deg": 148,
      "wave_height_m": 1.16,
      "cloud_pct": 0.0,
      "shadow_pct": 0.0,
      "snow_land_pct": 0.09,
      "valid_pct": 100.04,
      "quality_score": 100.0,
      "foam_fraction": 0.1862,
      "foam_extent_m": 96.5,
      "mean_nir": 411.2,
      "max_nir": 2412,
      "water_pixel_count": 1036,
      "foam_pixel_count": 192.94901960784313,
      "total_buffer_pixels": 1036
    },
    {
      "segment_id": "ns-seg-04002",
      "date": "2021-11-11",
      "swell_height_m": 0.36,
      "swell_period_s": 8.0,
      "swell_direction_deg": 114,
      "wave_height_m": 0.66,
      "cloud_pct": 0.11,
      "shadow_pct": 0.0,
      "snow_land_pct": 0.0,
      "valid_pct": 100.04,
      "quality_score": 100.0,
      "foam_fraction": 0.1561,
      "foam_extent_m": 81.2,
      "mean_nir": 374.8,
      "max_nir": 2640,
      "water_pixel_count": 1040,
      "foam_pixel_count": 162.30196078431374,
      "total_buffer_pixels": 1040
    },
    {
      "segment_id": "ns-seg-04002",
      "date": "2021-12-04",
      "swell_height_m": 0.9,
      "swell_period_s": 10.4,
      "swell_direction_deg": 206,
      "wave_height_m": 1.28,
      "cloud_pct": 0.02,
      "shadow_pct": 2.03,
      "snow_land_pct": 0.79,
      "valid_pct": 100.04,
      "quality_score": 99.6,
      "foam_fraction": 0.3863,
      "foam_extent_m": 238.1,
      "mean_nir": 711.4,
      "max_nir": 2444,
      "water_pixel_count": 1233,
      "foam_pixel_count": 476.2627450980393,
      "total_buffer_pixels": 1233
    },
    {
      "segment_id": "ns-seg-04002",
      "date": "2021-12-24",
      "swell_height_m": 0.66,
      "swell_period_s": 9.0,
      "swell_direction_deg": 184,
      "wave_height_m": 1.16,
      "cloud_pct": 3.0,
      "shadow_pct": 0.0,
      "snow_land_pct": 0.1,
      "valid_pct": 100.04,
      "quality_score": 98.8,
      "foam_fraction": 0.0,
      "foam_extent_m": 0.0,
      "mean_nir": 67.6,
      "max_nir": 289,
      "water_pixel_count": 446,
      "foam_pixel_count": 0,
      "total_buffer_pixels": 446
    },
    {
      "segment_id": "ns-seg-04002",
      "date": "2022-02-12",
      "swell_height_m": 0.82,
      "swell_period_s": 5.1,
      "swell_direction_deg": 164,
      "wave_height_m": 1.12,
      "cloud_pct": 3.4,
      "shadow_pct": 0.0,
      "snow_land_pct": 0.0,
      "valid_pct": 100.04,
      "quality_score": 98.6,
      "foam_fraction": 0.3483,
      "foam_extent_m": 176.2,
      "mean_nir": 628.5,
      "max_nir": 2646,
      "water_pixel_count": 1012,
      "foam_pixel_count": 352.4980392156863,
      "total_buffer_pixels": 1012
    },
    {
      "segment_id": "ns-seg-04002",
      "date": "2022-02-24",
      "swell_height_m": 0.9,
      "swell_period_s": 7.65,
      "swell_direction_deg": 197,
      "wave_height_m": 1.18,
      "cloud_pct": 0.88,
      "shadow_pct": 0.0,
      "snow_land_pct": 0.0,
      "valid_pct": 100.04,
      "quality_score": 99.6,
      "foam_fraction": 0.04,
      "foam_extent_m": 14.5,
      "mean_nir": 217.8,
      "max_nir": 1274,
      "water_pixel_count": 727,
      "foam_pixel_count": 29.07843137254902,
      "total_buffer_pixels": 727
    },
    {
      "segment_id": "ns-seg-04002",
      "date": "2022-03-11",
      "swell_height_m": 0.72,
      "swell_period_s": 7.35,
      "swell_direction_deg": 189,
      "wave_height_m": 0.9,
      "cloud_pct": 0.46,
      "shadow_pct": 0.0,
      "snow_land_pct": 0.04,
      "valid_pct": 100.04,
      "quality_score": 99.8,
      "foam_fraction": 0.0908,
      "foam_extent_m": 23.6,
      "mean_nir": 186.2,
      "max_nir": 2664,
      "water_pixel_count": 520,
      "foam_pixel_count": 47.21176470588236,
      "total_buffer_pixels": 520
    },
    {
      "segment_id": "ns-seg-04002",
      "date": "2022-04-05",
      "swell_height_m": 0.38,
      "swell_period_s": 7.4,
      "swell_direction_deg": 196,
      "wave_height_m": 0.54,
      "cloud_pct": 1.58,
      "shadow_pct": 0.0,
      "snow_land_pct": 0.0,
      "valid_pct": 100.04,
      "quality_score": 99.4,
      "foam_fraction": 0.0032,
      "foam_extent_m": 1.0,
      "mean_nir": 9.7,
      "max_nir": 1218,
      "water_pixel_count": 625,
      "foam_pixel_count": 2,
      "total_buffer_pixels": 625
    },
    {
      "segment_id": "ns-seg-04002",
      "date": "2022-04-18",
      "swell_height_m": 0.98,
      "swell_period_s": 7.8,
      "swell_direction_deg": 174,
      "wave_height_m": 1.14,
      "cloud_pct": 0.1,
      "shadow_pct": 0.0,
      "snow_land_pct": 0.0,
      "valid_pct": 100.04,
      "quality_score": 100.0,
      "foam_fraction": 0.1058,
      "foam_extent_m": 46.2,
      "mean_nir": 404.9,
      "max_nir": 2186,
      "water_pixel_count": 874,
      "foam_pixel_count": 92.45098039215686,
      "total_buffer_pixels": 874
    },
    {
      "segment_id": "ns-seg-04002",
      "date": "2022-05-10",
      "swell_height_m": 1.52,
      "swell_period_s": 7.9,
      "swell_direction_deg": 131,
      "wave_height_m": 1.88,
      "cloud_pct": 1.98,
      "shadow_pct": 0.0,
      "snow_land_pct": 2.69,
      "valid_pct": 100.04,
      "quality_score": 98.7,
      "foam_fraction": 0.0676,
      "foam_extent_m": 21.0,
      "mean_nir": 334.2,
      "max_nir": 2634,
      "water_pixel_count": 622,
      "foam_pixel_count": 42.050980392156866,
      "total_buffer_pixels": 622
    },
    {
      "segment_id": "ns-seg-04002",
      "date": "2022-05-25",
      "swell_height_m": 0.62,
      "swell_period_s": 6.4,
      "swell_direction_deg": 101,
      "wave_height_m": 0.66,
      "cloud_pct": 0.14,
      "shadow_pct": 0.0,
      "snow_land_pct": 0.0,
      "valid_pct": 100.04,
      "quality_score": 99.9,
      "foam_fraction": 0.3069,
      "foam_extent_m": 151.0,
      "mean_nir": 635.5,
      "max_nir": 3212,
      "water_pixel_count": 984,
      "foam_pixel_count": 302.0078431372549,
      "total_buffer_pixels": 984
    },
    {
      "segment_id": "ns-seg-04002",
      "date": "2022-06-07",
      "swell_height_m": 0.4,
      "swell_period_s": 11.55,
      "swell_direction_deg": 187,
      "wave_height_m": 0.58,
      "cloud_pct": 0.1,
      "shadow_pct": 0.0,
      "snow_land_pct": 0.0,
      "valid_pct": 100.04,
      "quality_score": 100.0,
      "foam_fraction": 0.1851,
      "foam_extent_m": 91.8,
      "mean_nir": 773.3,
      "max_nir": 3042,
      "water_pixel_count": 992,
      "foam_pixel_count": 183.64313725490197,
      "total_buffer_pixels": 992
    },
    {
      "segment_id": "ns-seg-04002",
      "date": "2022-06-12",
      "swell_height_m": 0.76,
      "swell_period_s": 6.75,
      "swell_direction_deg": 158,
      "wave_height_m": 0.96,
      "cloud_pct": 7.49,
      "shadow_pct": 0.02,
      "snow_land_pct": 0.0,
      "valid_pct": 100.04,
      "quality_score": 97.0,
      "foam_fraction": 0.3487,
      "foam_extent_m": 243.1,
      "mean_nir": 925.7,
      "max_nir": 4504,
      "water_pixel_count": 1394,
      "foam_pixel_count": 486.1058823529412,
      "total_buffer_pixels": 1394
    },
    {
      "segment_id": "ns-seg-04002",
      "date": "2022-06-19",
      "swell_height_m": 1.62,
      "swell_period_s": 7.8,
      "swell_direction_deg": 166,
      "wave_height_m": 1.78,
      "cloud_pct": 0.3,
      "shadow_pct": 1.51,
      "snow_land_pct": 0.5,
      "valid_pct": 100.04,
      "quality_score": 99.6,
      "foam_fraction": 0.1922,
      "foam_extent_m": 93.6,
      "mean_nir": 552.8,
      "max_nir": 3664,
      "water_pixel_count": 974,
      "foam_pixel_count": 187.1843137254902,
      "total_buffer_pixels": 974
    },
    {
      "segment_id": "ns-seg-04002",
      "date": "2022-07-04",
      "swell_height_m": 0.74,
      "swell_period_s": 5.0,
      "swell_direction_deg": 188,
      "wave_height_m": 0.8,
      "cloud_pct": 0.0,
      "shadow_pct": 0.0,
      "snow_land_pct": 0.0,
      "valid_pct": 100.04,
      "quality_score": 100.0,
      "foam_fraction": 0.1444,
      "foam_extent_m": 71.3,
      "mean_nir": 397.3,
      "max_nir": 3288,
      "water_pixel_count": 988,
      "foam_pixel_count": 142.64313725490197,
      "total_buffer_pixels": 988
    },
    {
      "segment_id": "ns-seg-04002",
      "date": "2022-07-07",
      "swell_height_m": 0.5,
      "swell_period_s": 5.1,
      "swell_direction_deg": 173,
      "wave_height_m": 0.68,
      "cloud_pct": 3.08,
      "shadow_pct": 4.44,
      "snow_land_pct": 0.0,
      "valid_pct": 100.04,
      "quality_score": 98.3,
      "foam_fraction": 0.2013,
      "foam_extent_m": 97.4,
      "mean_nir": 773.7,
      "max_nir": 3488,
      "water_pixel_count": 968,
      "foam_pixel_count": 194.8392156862745,
      "total_buffer_pixels": 968
    },
    {
      "segment_id": "ns-seg-04002",
      "date": "2022-07-09",
      "swell_height_m": 0.46,
      "swell_period_s": 6.8,
      "swell_direction_deg": 179,
      "wave_height_m": 0.72,
      "cloud_pct": 0.07,
      "shadow_pct": 0.0,
      "snow_land_pct": 0.0,
      "valid_pct": 100.04,
      "quality_score": 100.0,
      "foam_fraction": 0.2395,
      "foam_extent_m": 114.0,
      "mean_nir": 514.0,
      "max_nir": 3644,
      "water_pixel_count": 952,
      "foam_pixel_count": 228.0078431372549,
      "total_buffer_pixels": 952
    },
    {
      "segment_id": "ns-seg-04002",
      "date": "2022-07-12",
      "swell_height_m": 0.4,
      "swell_period_s": 5.1,
      "swell_direction_deg": 161,
      "wave_height_m": 0.58,
      "cloud_pct": 0.11,
      "shadow_pct": 0.0,
      "snow_land_pct": 0.0,
      "valid_pct": 100.04,
      "quality_score": 100.0,
      "foam_fraction": 0.2853,
      "foam_extent_m": 137.5,
      "mean_nir": 765.9,
      "max_nir": 3336,
      "water_pixel_count": 964,
      "foam_pixel_count": 275.0078431372549,
      "total_buffer_pixels": 964
    },
    {
      "segment_id": "ns-seg-04002",
      "date": "2022-08-21",
      "swell_height_m": 0.32,
      "swell_period_s": 7.15,
      "swell_direction_deg": 161,
      "wave_height_m": 0.48,
      "cloud_pct": 0.0,
      "shadow_pct": 0.0,
      "snow_land_pct": 0.0,
      "valid_pct": 100.04,
      "quality_score": 100.0,
      "foam_fraction": 0.1893,
      "foam_extent_m": 91.6,
      "mean_nir": 441.8,
      "max_nir": 2840,
      "water_pixel_count": 968,
      "foam_pixel_count": 183.20392156862744,
      "total_buffer_pixels": 968
    },
    {
      "segment_id": "ns-seg-04002",
      "date": "2022-08-28",
      "swell_height_m": 0.42,
      "swell_period_s": 5.0,
      "swell_direction_deg": 176,
      "wave_height_m": 0.58,
      "cloud_pct": 0.0,
      "shadow_pct": 0.0,
      "snow_land_pct": 0.0,
      "valid_pct": 100.04,
      "quality_score": 100.0,
      "foam_fraction": 0.1569,
      "foam_extent_m": 77.8,
      "mean_nir": 367.9,
      "max_nir": 2906,
      "water_pixel_count": 992,
      "foam_pixel_count": 155.64313725490197,
      "total_buffer_pixels": 992
    },
    {
      "segment_id": "ns-seg-04002",
      "date": "2022-09-02",
      "swell_height_m": 0.48,
      "swell_period_s": 5.7,
      "swell_direction_deg": 116,
      "wave_height_m": 0.76,
      "cloud_pct": 17.13,
      "shadow_pct": 15.25,
      "snow_land_pct": 0.0,
      "valid_pct": 100.04,
      "quality_score": 91.6,
      "foam_fraction": 0.0759,
      "foam_extent_m": 87.8,
      "mean_nir": 380.3,
      "max_nir": 4260,
      "water_pixel_count": 2313,
      "foam_pixel_count": 175.57647058823528,
      "total_buffer_pixels": 2313
    },
    {
      "segment_id": "ns-seg-04002",
      "date": "2022-09-07",
      "swell_height_m": 0.56,
      "swell_period_s": 6.25,
      "swell_direction_deg": 109,
      "wave_height_m": 0.78,
      "cloud_pct": 55.4,
      "shadow_pct": 18.97,
      "snow_land_pct": 0.0,
      "valid_pct": 100.04,
      "quality_score": 75.9,
      "foam_fraction": 0.4607,
      "foam_extent_m": 407.5,
      "mean_nir": 1019.7,
      "max_nir": 4620,
      "water_pixel_count": 1769,
      "foam_pixel_count": 815.0196078431374,
      "total_buffer_pixels": 1769
    },
    {
      "segment_id": "ns-seg-04002",
      "date": "2022-09-10",
      "swell_height_m": 1.62,
      "swell_period_s": 8.0,
      "swell_direction_deg": 103,
      "wave_height_m": 2.02,
      "cloud_pct": 0.76,
      "shadow_pct": 0.3,
      "snow_land_pct": 1.05,
      "valid_pct": 100.04,
      "quality_score": 99.5,
      "foam_fraction": 0.2676,
      "foam_extent_m": 134.3,
      "mean_nir": 575.3,
      "max_nir": 2684,
      "water_pixel_count": 1004,
      "foam_pixel_count": 268.6980392156863,
      "total_buffer_pixels": 1004
    },
    {
      "segment_id": "ns-seg-04002",
      "date": "2022-09-17",
      "swell_height_m": 0.18,
      "swell_period_s": 4.15,
      "swell_direction_deg": 241,
      "wave_height_m": 0.42,
      "cloud_pct": 0.08,
      "shadow_pct": 0.0,
      "snow_land_pct": 0.0,
      "valid_pct": 100.04,
      "quality_score": 100.0,
      "foam_fraction": 0.1269,
      "foam_extent_m": 61.7,
      "mean_nir": 313.8,
      "max_nir": 2762,
      "water_pixel_count": 972,
      "foam_pixel_count": 123.36470588235295,
      "total_buffer_pixels": 972
    },
    {
      "segment_id": "ns-seg-04002",
      "date": "2022-09-25",
      "swell_height_m": 0.82,
      "swell_period_s": 9.15,
      "swell_direction_deg": 168,
      "wave_height_m": 1.18,
      "cloud_pct": 0.01,
      "shadow_pct": 0.0,
      "snow_land_pct": 0.0,
      "valid_pct": 100.04,
      "quality_score": 100.0,
      "foam_fraction": 0.2311,
      "foam_extent_m": 113.3,
      "mean_nir": 471.5,
      "max_nir": 2532,
      "water_pixel_count": 980,
      "foam_pixel_count": 226.50980392156862,
      "total_buffer_pixels": 980
    },
    {
      "segment_id": "ns-seg-04002",
      "date": "2022-09-30",
      "swell_height_m": 0.4,
      "swell_period_s": 5.45,
      "swell_direction_deg": 146,
      "wave_height_m": 0.58,
      "cloud_pct": 0.45,
      "shadow_pct": 0.0,
      "snow_land_pct": 0.0,
      "valid_pct": 100.04,
      "quality_score": 99.8,
      "foam_fraction": 0.5977,
      "foam_extent_m": 243.3,
      "mean_nir": 1159.0,
      "max_nir": 3440,
      "water_pixel_count": 814,
      "foam_pixel_count": 486.5215686274509,
      "total_buffer_pixels": 814
    },
    {
      "segment_id": "ns-seg-04002",
      "date": "2022-10-12",
      "swell_height_m": 0.34,
      "swell_period_s": 9.3,
      "swell_direction_deg": 138,
      "wave_height_m": 0.46,
      "cloud_pct": 0.08,
      "shadow_pct": 0.0,
      "snow_land_pct": 0.0,
      "valid_pct": 100.04,
      "quality_score": 100.0,
      "foam_fraction": 0.1235,
      "foam_extent_m": 61.2,
      "mean_nir": 266.0,
      "max_nir": 2720,
      "water_pixel_count": 991,
      "foam_pixel_count": 122.36470588235295,
      "total_buffer_pixels": 991
    },
    {
      "segment_id": "ns-seg-04002",
      "date": "2022-10-30",
      "swell_height_m": 0.38,
      "swell_period_s": 7.7,
      "swell_direction_deg": 141,
      "wave_height_m": 0.52,
      "cloud_pct": 0.01,
      "shadow_pct": 0.0,
      "snow_land_pct": 0.0,
      "valid_pct": 100.04,
      "quality_score": 100.0,
      "foam_fraction": 0.1083,
      "foam_extent_m": 54.6,
      "mean_nir": 248.6,
      "max_nir": 2364,
      "water_pixel_count": 1008,
      "foam_pixel_count": 109.20392156862745,
      "total_buffer_pixels": 1008
    },
    {
      "segment_id": "ns-seg-04002",
      "date": "2022-11-09",
      "swell_height_m": 0.26,
      "swell_period_s": 10.95,
      "swell_direction_deg": 175,
      "wave_height_m": 0.44,
      "cloud_pct": 0.0,
      "shadow_pct": 0.0,
      "snow_land_pct": 0.0,
      "valid_pct": 100.04,
      "quality_score": 100.0,
      "foam_fraction": 0.147,
      "foam_extent_m": 74.1,
      "mean_nir": 337.3,
      "max_nir": 2424,
      "water_pixel_count": 1008,
      "foam_pixel_count": 148.20392156862744,
      "total_buffer_pixels": 1008
    },
    {
      "segment_id": "ns-seg-04002",
      "date": "2022-11-21",
      "swell_height_m": 0.66,
      "swell_period_s": 5.25,
      "swell_direction_deg": 228,
      "wave_height_m": 1.16,
      "cloud_pct": 0.05,
      "shadow_pct": 0.0,
      "snow_land_pct": 0.02,
      "valid_pct": 100.04,
      "quality_score": 100.0,
      "foam_fraction": 0.3559,
      "foam_extent_m": 164.8,
      "mean_nir": 650.8,
      "max_nir": 2352,
      "water_pixel_count": 926,
      "foam_pixel_count": 329.5176470588235,
      "total_buffer_pixels": 926
    },
    {
      "segment_id": "ns-seg-04002",
      "date": "2022-11-24",
      "swell_height_m": 0.22,
      "swell_period_s": 6.45,
      "swell_direction_deg": 215,
      "wave_height_m": 0.46,
      "cloud_pct": 0.99,
      "shadow_pct": 0.0,
      "snow_land_pct": 0.0,
      "valid_pct": 100.04,
      "quality_score": 99.6,
      "foam_fraction": 0.1277,
      "foam_extent_m": 57.0,
      "mean_nir": 310.6,
      "max_nir": 2218,
      "water_pixel_count": 892,
      "foam_pixel_count": 113.91372549019607,
      "total_buffer_pixels": 892
    },
    {
      "segment_id": "ns-seg-04002",
      "date": "2022-11-29",
      "swell_height_m": 0.92,
      "swell_period_s": 9.0,
      "swell_direction_deg": 200,
      "wave_height_m": 1.12,
      "cloud_pct": 0.05,
      "shadow_pct": 0.0,
      "snow_land_pct": 0.21,
      "valid_pct": 100.04,
      "quality_score": 99.9,
      "foam_fraction": 0.1787,
      "foam_extent_m": 93.7,
      "mean_nir": 403.9,
      "max_nir": 2526,
      "water_pixel_count": 1048,
      "foam_pixel_count": 187.3294117647059,
      "total_buffer_pixels": 1048
    },
    {
      "segment_id": "ns-seg-04002",
      "date": "2023-01-25",
      "swell_height_m": 0.8,
      "swell_period_s": 8.85,
      "swell_direction_deg": 154,
      "wave_height_m": 1.06,
      "cloud_pct": 0.47,
      "shadow_pct": 0.0,
      "snow_land_pct": 0.5,
      "valid_pct": 100.04,
      "quality_score": 99.7,
      "foam_fraction": 0.098,
      "foam_extent_m": 44.4,
      "mean_nir": 281.0,
      "max_nir": 2466,
      "water_pixel_count": 905,
      "foam_pixel_count": 88.72941176470589,
      "total_buffer_pixels": 905
    },
    {
      "segment_id": "ns-seg-04002",
      "date": "2023-02-09",
      "swell_height_m": 0.48,
      "swell_period_s": 8.45,
      "swell_direction_deg": 111,
      "wave_height_m": 0.8,
      "cloud_pct": 0.94,
      "shadow_pct": 0.0,
      "snow_land_pct": 0.0,
      "valid_pct": 100.04,
      "quality_score": 99.6,
      "foam_fraction": 0.0172,
      "foam_extent_m": 6.6,
      "mean_nir": 83.9,
      "max_nir": 2520,
      "water_pixel_count": 763,
      "foam_pixel_count": 13.152941176470588,
      "total_buffer_pixels": 763
    },
    {
      "segment_id": "ns-seg-04002",
      "date": "2023-02-22",
      "swell_height_m": 0.92,
      "swell_period_s": 8.05,
      "swell_direction_deg": 126,
      "wave_height_m": 1.22,
      "cloud_pct": 0.05,
      "shadow_pct": 0.0,
      "snow_land_pct": 0.98,
      "valid_pct": 100.04,
      "quality_score": 99.8,
      "foam_fraction": 0.3523,
      "foam_extent_m": 173.9,
      "mean_nir": 689.7,
      "max_nir": 2700,
      "water_pixel_count": 987,
      "foam_pixel_count": 347.7137254901961,
      "total_buffer_pixels": 987
    },
    {
      "segment_id": "ns-seg-04002",
      "date": "2023-03-11",
      "swell_height_m": 0.48,
      "swell_period_s": 9.7,
      "swell_direction_deg": 92,
      "wave_height_m": 0.58,
      "cloud_pct": 0.02,
      "shadow_pct": 0.0,
      "snow_land_pct": 76.93,
      "valid_pct": 100.04,
      "quality_score": 84.6,
      "foam_fraction": 0.164,
      "foam_extent_m": 83.5,
      "mean_nir": 394.1,
      "max_nir": 4680,
      "water_pixel_count": 1018,
      "foam_pixel_count": 166.98039215686276,
      "total_buffer_pixels": 1018
    },
    {
      "segment_id": "ns-seg-04002",
      "date": "2023-03-19",
      "swell_height_m": 0.94,
      "swell_period_s": 7.95,
      "swell_direction_deg": 191,
      "wave_height_m": 1.18,
      "cloud_pct": 0.02,
      "shadow_pct": 0.0,
      "snow_land_pct": 2.59,
      "valid_pct": 100.04,
      "quality_score": 99.5,
      "foam_fraction": 0.4223,
      "foam_extent_m": 193.4,
      "mean_nir": 668.9,
      "max_nir": 2062,
      "water_pixel_count": 916,
      "foam_pixel_count": 386.84705882352944,
      "total_buffer_pixels": 916
    },
    {
      "segment_id": "ns-seg-04002",
      "date": "2023-03-21",
      "swell_height_m": 0.64,
      "swell_period_s": 5.45,
      "swell_direction_deg": 196,
      "wave_height_m": 0.8,
      "cloud_pct": 0.0,
      "shadow_pct": 0.0,
      "snow_land_pct": 0.0,
      "valid_pct": 100.04,
      "quality_score": 100.0,
      "foam_fraction": 0.242,
      "foam_extent_m": 117.6,
      "mean_nir": 542.6,
      "max_nir": 2328,
      "water_pixel_count": 972,
      "foam_pixel_count": 235.20392156862744,
      "total_buffer_pixels": 972
    },
    {
      "segment_id": "ns-seg-04002",
      "date": "2023-04-08",
      "swell_height_m": 0.36,
      "swell_period_s": 5.4,
      "swell_direction_deg": 205,
      "wave_height_m": 0.52,
      "cloud_pct": 1.04,
      "shadow_pct": 0.0,
      "snow_land_pct": 0.0,
      "valid_pct": 100.04,
      "quality_score": 99.6,
      "foam_fraction": 0.0092,
      "foam_extent_m": 3.0,
      "mean_nir": 135.2,
      "max_nir": 1784,
      "water_pixel_count": 651,
      "foam_pixel_count": 6,
      "total_buffer_pixels": 651
    },
    {
      "segment_id": "ns-seg-04002",
      "date": "2023-04-10",
      "swell_height_m": 0.34,
      "swell_period_s": 3.8,
      "swell_direction_deg": 211,
      "wave_height_m": 0.5,
      "cloud_pct": 0.06,
      "shadow_pct": 0.0,
      "snow_land_pct": 0.0,
      "valid_pct": 100.04,
      "quality_score": 100.0,
      "foam_fraction": 0.0843,
      "foam_extent_m": 38.7,
      "mean_nir": 223.6,
      "max_nir": 2068,
      "water_pixel_count": 918,
      "foam_pixel_count": 77.3686274509804,
      "total_buffer_pixels": 918
    },
    {
      "segment_id": "ns-seg-04002",
      "date": "2023-04-13",
      "swell_height_m": 0.48,
      "swell_period_s": 7.85,
      "swell_direction_deg": 156,
      "wave_height_m": 0.7,
      "cloud_pct": 0.0,
      "shadow_pct": 0.0,
      "snow_land_pct": 0.0,
      "valid_pct": 100.04,
      "quality_score": 100.0,
      "foam_fraction": 0.1575,
      "foam_extent_m": 75.6,
      "mean_nir": 404.1,
      "max_nir": 2176,
      "water_pixel_count": 960,
      "foam_pixel_count": 151.20392156862744,
      "total_buffer_pixels": 960
    },
    {
      "segment_id": "ns-seg-04002",
      "date": "2023-04-28",
      "swell_height_m": 0.48,
      "swell_period_s": 8.5,
      "swell_direction_deg": 98,
      "wave_height_m": 0.58,
      "cloud_pct": 0.08,
      "shadow_pct": 0.0,
      "snow_land_pct": 0.0,
      "valid_pct": 100.04,
      "quality_score": 100.0,
      "foam_fraction": 0.2713,
      "foam_extent_m": 123.2,
      "mean_nir": 608.9,
      "max_nir": 2340,
      "water_pixel_count": 908,
      "foam_pixel_count": 246.30196078431374,
      "total_buffer_pixels": 908
    },
    {
      "segment_id": "ns-seg-04002",
      "date": "2023-05-23",
      "swell_height_m": 0.66,
      "swell_period_s": 6.85,
      "swell_direction_deg": 150,
      "wave_height_m": 0.78,
      "cloud_pct": 0.06,
      "shadow_pct": 0.0,
      "snow_land_pct": 0.0,
      "valid_pct": 100.04,
      "quality_score": 100.0,
      "foam_fraction": 0.1929,
      "foam_extent_m": 89.1,
      "mean_nir": 620.4,
      "max_nir": 2580,
      "water_pixel_count": 924,
      "foam_pixel_count": 178.27058823529413,
      "total_buffer_pixels": 924
    },
    {
      "segment_id": "ns-seg-04002",
      "date": "2023-05-28",
      "swell_height_m": 0.36,
      "swell_period_s": 4.3,
      "swell_direction_deg": 179,
      "wave_height_m": 0.76,
      "cloud_pct": 0.06,
      "shadow_pct": 0.0,
      "snow_land_pct": 0.0,
      "valid_pct": 100.04,
      "quality_score": 100.0,
      "foam_fraction": 0.3553,
      "foam_extent_m": 157.1,
      "mean_nir": 804.1,
      "max_nir": 2598,
      "water_pixel_count": 884,
      "foam_pixel_count": 314.11764705882354,
      "total_buffer_pixels": 884
    },
    {
      "segment_id": "ns-seg-04002",
      "date": "2023-05-30",
      "swell_height_m": 0.28,
      "swell_period_s": 9.5,
      "swell_direction_deg": 152,
      "wave_height_m": 0.4,
      "cloud_pct": 0.17,
      "shadow_pct": 0.0,
      "snow_land_pct": 0.0,
      "valid_pct": 100.04,
      "quality_score": 99.9,
      "foam_fraction": 0.4844,
      "foam_extent_m": 221.8,
      "mean_nir": 886.8,
      "max_nir": 2852,
      "water_pixel_count": 916,
      "foam_pixel_count": 443.69019607843137,
      "total_buffer_pixels": 916
    },
    {
      "segment_id": "ns-seg-04002",
      "date": "2023-06-22",
      "swell_height_m": 0.28,
      "swell_period_s": 5.65,
      "swell_direction_deg": 179,
      "wave_height_m": 0.38,
      "cloud_pct": 0.02,
      "shadow_pct": 0.0,
      "snow_land_pct": 0.0,
      "valid_pct": 100.04,
      "quality_score": 100.0,
      "foam_fraction": 0.1727,
      "foam_extent_m": 79.1,
      "mean_nir": 749.8,
      "max_nir": 2670,
      "water_pixel_count": 916,
      "foam_pixel_count": 158.20392156862744,
      "total_buffer_pixels": 916
    },
    {
      "segment_id": "ns-seg-04002",
      "date": "2023-07-14",
      "swell_height_m": 0.66,
      "swell_period_s": 7.05,
      "swell_direction_deg": 117,
      "wave_height_m": 0.86,
      "cloud_pct": 0.07,
      "shadow_pct": 0.0,
      "snow_land_pct": 0.0,
      "valid_pct": 100.04,
      "quality_score": 100.0,
      "foam_fraction": 0.3706,
      "foam_extent_m": 171.2,
      "mean_nir": 734.2,
      "max_nir": 2966,
      "water_pixel_count": 924,
      "foam_pixel_count": 342.4666666666667,
      "total_buffer_pixels": 924
    },
    {
      "segment_id": "ns-seg-04002",
      "date": "2023-08-03",
      "swell_height_m": 0.42,
      "swell_period_s": 8.5,
      "swell_direction_deg": 145,
      "wave_height_m": 0.62,
      "cloud_pct": 0.0,
      "shadow_pct": 0.0,
      "snow_land_pct": 0.0,
      "valid_pct": 100.04,
      "quality_score": 100.0,
      "foam_fraction": 0.1795,
      "foam_extent_m": 86.9,
      "mean_nir": 475.3,
      "max_nir": 2968,
      "water_pixel_count": 968,
      "foam_pixel_count": 173.80392156862746,
      "total_buffer_pixels": 968
    },
    {
      "segment_id": "ns-seg-04002",
      "date": "2023-08-23",
      "swell_height_m": 0.34,
      "swell_period_s": 9.1,
      "swell_direction_deg": 132,
      "wave_height_m": 0.44,
      "cloud_pct": 0.0,
      "shadow_pct": 0.52,
      "snow_land_pct": 0.0,
      "valid_pct": 100.04,
      "quality_score": 99.9,
      "foam_fraction": 0.1491,
      "foam_extent_m": 70.7,
      "mean_nir": 384.6,
      "max_nir": 2998,
      "water_pixel_count": 948,
      "foam_pixel_count": 141.36470588235295,
      "total_buffer_pixels": 948
    },
    {
      "segment_id": "ns-seg-04002",
      "date": "2023-08-28",
      "swell_height_m": 0.64,
      "swell_period_s": 4.8,
      "swell_direction_deg": 146,
      "wave_height_m": 0.82,
      "cloud_pct": 19.03,
      "shadow_pct": 14.77,
      "snow_land_pct": 0.0,
      "valid_pct": 100.04,
      "quality_score": 90.9,
      "foam_fraction": 0.3432,
      "foam_extent_m": 170.9,
      "mean_nir": 715.2,
      "max_nir": 4796,
      "water_pixel_count": 996,
      "foam_pixel_count": 341.8,
      "total_buffer_pixels": 996
    },
    {
      "segment_id": "ns-seg-04002",
      "date": "2023-09-02",
      "swell_height_m": 0.64,
      "swell_period_s": 8.2,
      "swell_direction_deg": 140,
      "wave_height_m": 0.72,
      "cloud_pct": 0.0,
      "shadow_pct": 0.0,
      "snow_land_pct": 0.0,
      "valid_pct": 100.04,
      "quality_score": 100.0,
      "foam_fraction": 0.0854,
      "foam_extent_m": 29.3,
      "mean_nir": 195.4,
      "max_nir": 2166,
      "water_pixel_count": 686,
      "foam_pixel_count": 58.6,
      "total_buffer_pixels": 686
    },
    {
      "segment_id": "ns-seg-04002",
      "date": "2023-09-27",
      "swell_height_m": 0.62,
      "swell_period_s": 6.65,
      "swell_direction_deg": 123,
      "wave_height_m": 0.64,
      "cloud_pct": 49.93,
      "shadow_pct": 0.0,
      "snow_land_pct": 6.27,
      "valid_pct": 100.04,
      "quality_score": 78.8,
      "foam_fraction": 0.9859,
      "foam_extent_m": 180.9,
      "mean_nir": 2575.1,
      "max_nir": 3340,
      "water_pixel_count": 367,
      "foam_pixel_count": 361.8352941176471,
      "total_buffer_pixels": 367
    },
    {
      "segment_id": "ns-seg-04002",
      "date": "2023-10-02",
      "swell_height_m": 0.96,
      "swell_period_s": 7.9,
      "swell_direction_deg": 147,
      "wave_height_m": 1.04,
      "cloud_pct": 0.02,
      "shadow_pct": 0.0,
      "snow_land_pct": 0.02,
      "valid_pct": 100.04,
      "quality_score": 100.0,
      "foam_fraction": 0.2238,
      "foam_extent_m": 111.8,
      "mean_nir": 502.2,
      "max_nir": 2756,
      "water_pixel_count": 999,
      "foam_pixel_count": 223.6235294117647,
      "total_buffer_pixels": 999
    },
    {
      "segment_id": "ns-seg-04002",
      "date": "2023-10-10",
      "swell_height_m": 0.78,
      "swell_period_s": 4.75,
      "swell_direction_deg": 152,
      "wave_height_m": 1.04,
      "cloud_pct": 0.0,
      "shadow_pct": 0.0,
      "snow_land_pct": 0.52,
      "valid_pct": 100.04,
      "quality_score": 99.9,
      "foam_fraction": 0.2963,
      "foam_extent_m": 145.2,
      "mean_nir": 599.3,
      "max_nir": 2676,
      "water_pixel_count": 980,
      "foam_pixel_count": 290.4078431372549,
      "total_buffer_pixels": 980
    },
    {
      "segment_id": "ns-seg-04002",
      "date": "2023-10-12",
      "swell_height_m": 0.64,
      "swell_period_s": 4.85,
      "swell_direction_deg": 151,
      "wave_height_m": 0.9,
      "cloud_pct": 0.0,
      "shadow_pct": 0.0,
      "snow_land_pct": 0.0,
      "valid_pct": 100.04,
      "quality_score": 100.0,
      "foam_fraction": 0.2815,
      "foam_extent_m": 140.2,
      "mean_nir": 524.0,
      "max_nir": 2664,
      "water_pixel_count": 996,
      "foam_pixel_count": 280.4117647058824,
      "total_buffer_pixels": 996
    },
    {
      "segment_id": "ns-seg-04002",
      "date": "2023-11-19",
      "swell_height_m": 3.5,
      "swell_period_s": 10.65,
      "swell_direction_deg": 162,
      "wave_height_m": 3.5,
      "cloud_pct": 1.2,
      "shadow_pct": 0.0,
      "snow_land_pct": 13.06,
      "valid_pct": 100.04,
      "quality_score": 96.9,
      "foam_fraction": 0.3393,
      "foam_extent_m": 163.4,
      "mean_nir": 753.7,
      "max_nir": 3240,
      "water_pixel_count": 963,
      "foam_pixel_count": 326.756862745098,
      "total_buffer_pixels": 963
    },
    {
      "segment_id": "ns-seg-04002",
      "date": "2023-11-21",
      "swell_height_m": 0.82,
      "swell_period_s": 8.95,
      "swell_direction_deg": 149,
      "wave_height_m": 0.98,
      "cloud_pct": 0.27,
      "shadow_pct": 0.0,
      "snow_land_pct": 0.0,
      "valid_pct": 100.04,
      "quality_score": 99.9,
      "foam_fraction": 0.2663,
      "foam_extent_m": 133.1,
      "mean_nir": 552.5,
      "max_nir": 2652,
      "water_pixel_count": 1000,
      "foam_pixel_count": 266.26666666666665,
      "total_buffer_pixels": 1000
    },
    {
      "segment_id": "ns-seg-04002",
      "date": "2023-12-09",
      "swell_height_m": 0.3,
      "swell_period_s": 9.55,
      "swell_direction_deg": 131,
      "wave_height_m": 0.42,
      "cloud_pct": 0.0,
      "shadow_pct": 0.0,
      "snow_land_pct": 86.21,
      "valid_pct": 100.04,
      "quality_score": 82.8,
      "foam_fraction": 0.1627,
      "foam_extent_m": 77.8,
      "mean_nir": 346.3,
      "max_nir": 6988,
      "water_pixel_count": 956,
      "foam_pixel_count": 155.50980392156862,
      "total_buffer_pixels": 956
    },
    {
      "segment_id": "ns-seg-04002",
      "date": "2024-03-20",
      "swell_height_m": 0.66,
      "swell_period_s": 5.05,
      "swell_direction_deg": 196,
      "wave_height_m": 0.86,
      "cloud_pct": 0.0,
      "shadow_pct": 0.0,
      "snow_land_pct": 0.02,
      "valid_pct": 100.04,
      "quality_score": 100.0,
      "foam_fraction": 0.2662,
      "foam_extent_m": 132.0,
      "mean_nir": 483.8,
      "max_nir": 2480,
      "water_pixel_count": 992,
      "foam_pixel_count": 264.0235294117647,
      "total_buffer_pixels": 992
    },
    {
      "segment_id": "ns-seg-04002",
      "date": "2024-04-02",
      "swell_height_m": 0.34,
      "swell_period_s": 6.9,
      "swell_direction_deg": 142,
      "wave_height_m": 0.58,
      "cloud_pct": 0.05,
      "shadow_pct": 0.0,
      "snow_land_pct": 0.0,
      "valid_pct": 100.04,
      "quality_score": 100.0,
      "foam_fraction": 0.1992,
      "foam_extent_m": 100.0,
      "mean_nir": 418.5,
      "max_nir": 2310,
      "water_pixel_count": 1004,
      "foam_pixel_count": 199.94901960784313,
      "total_buffer_pixels": 1004
    },
    {
      "segment_id": "ns-seg-04002",
      "date": "2024-04-27",
      "swell_height_m": 0.42,
      "swell_period_s": 6.65,
      "swell_direction_deg": 132,
      "wave_height_m": 0.56,
      "cloud_pct": 0.03,
      "shadow_pct": 0.0,
      "snow_land_pct": 0.0,
      "valid_pct": 100.04,
      "quality_score": 100.0,
      "foam_fraction": 0.169,
      "foam_extent_m": 84.3,
      "mean_nir": 465.1,
      "max_nir": 2430,
      "water_pixel_count": 998,
      "foam_pixel_count": 168.64705882352942,
      "total_buffer_pixels": 998
    },
    {
      "segment_id": "ns-seg-04002",
      "date": "2024-05-14",
      "swell_height_m": 0.58,
      "swell_period_s": 7.0,
      "swell_direction_deg": 132,
      "wave_height_m": 0.62,
      "cloud_pct": 0.0,
      "shadow_pct": 0.0,
      "snow_land_pct": 0.0,
      "valid_pct": 100.04,
      "quality_score": 100.0,
      "foam_fraction": 0.1623,
      "foam_extent_m": 81.5,
      "mean_nir": 365.9,
      "max_nir": 2668,
      "water_pixel_count": 1004,
      "foam_pixel_count": 162.94901960784313,
      "total_buffer_pixels": 1004
    },
    {
      "segment_id": "ns-seg-04002",
      "date": "2024-05-29",
      "swell_height_m": 1.42,
      "swell_period_s": 6.4,
      "swell_direction_deg": 159,
      "wave_height_m": 1.54,
      "cloud_pct": 0.32,
      "shadow_pct": 0.31,
      "snow_land_pct": 0.19,
      "valid_pct": 100.04,
      "quality_score": 99.8,
      "foam_fraction": 0.2383,
      "foam_extent_m": 119.4,
      "mean_nir": 554.8,
      "max_nir": 3648,
      "water_pixel_count": 1002,
      "foam_pixel_count": 238.7529411764706,
      "total_buffer_pixels": 1002
    },
    {
      "segment_id": "ns-seg-04002",
      "date": "2024-06-16",
      "swell_height_m": 0.86,
      "swell_period_s": 7.2,
      "swell_direction_deg": 175,
      "wave_height_m": 0.98,
      "cloud_pct": 0.26,
      "shadow_pct": 0.0,
      "snow_land_pct": 0.0,
      "valid_pct": 100.04,
      "quality_score": 99.9,
      "foam_fraction": 0.3003,
      "foam_extent_m": 145.1,
      "mean_nir": 878.6,
      "max_nir": 3444,
      "water_pixel_count": 966,
      "foam_pixel_count": 290.1058823529412,
      "total_buffer_pixels": 966
    },
    {
      "segment_id": "ns-seg-04002",
      "date": "2024-06-21",
      "swell_height_m": 0.42,
      "swell_period_s": 4.35,
      "swell_direction_deg": 204,
      "wave_height_m": 0.48,
      "cloud_pct": 0.11,
      "shadow_pct": 0.0,
      "snow_land_pct": 0.0,
      "valid_pct": 100.04,
      "quality_score": 100.0,
      "foam_fraction": 0.2095,
      "foam_extent_m": 101.8,
      "mean_nir": 695.6,
      "max_nir": 3144,
      "water_pixel_count": 972,
      "foam_pixel_count": 203.64313725490197,
      "total_buffer_pixels": 972
    },
    {
      "segment_id": "ns-seg-04002",
      "date": "2024-06-28",
      "swell_height_m": 0.78,
      "swell_period_s": 4.8,
      "swell_direction_deg": 180,
      "wave_height_m": 0.86,
      "cloud_pct": 0.13,
      "shadow_pct": 0.0,
      "snow_land_pct": 0.0,
      "valid_pct": 100.04,
      "quality_score": 99.9,
      "foam_fraction": 0.1355,
      "foam_extent_m": 66.4,
      "mean_nir": 392.0,
      "max_nir": 3716,
      "water_pixel_count": 980,
      "foam_pixel_count": 132.80392156862746,
      "total_buffer_pixels": 980
    },
    {
      "segment_id": "ns-seg-04002",
      "date": "2024-07-03",
      "swell_height_m": 0.7,
      "swell_period_s": 6.7,
      "swell_direction_deg": 160,
      "wave_height_m": 0.8,
      "cloud_pct": 0.02,
      "shadow_pct": 0.0,
      "snow_land_pct": 0.0,
      "valid_pct": 100.04,
      "quality_score": 100.0,
      "foam_fraction": 0.2409,
      "foam_extent_m": 115.7,
      "mean_nir": 602.4,
      "max_nir": 3344,
      "water_pixel_count": 960,
      "foam_pixel_count": 231.30196078431374,
      "total_buffer_pixels": 960
    },
    {
      "segment_id": "ns-seg-04002",
      "date": "2024-07-28",
      "swell_height_m": 0.36,
      "swell_period_s": 4.4,
      "swell_direction_deg": 183,
      "wave_height_m": 0.52,
      "cloud_pct": 0.02,
      "shadow_pct": 0.0,
      "snow_land_pct": 0.0,
      "valid_pct": 100.04,
      "quality_score": 100.0,
      "foam_fraction": 0.1613,
      "foam_extent_m": 79.7,
      "mean_nir": 470.8,
      "max_nir": 3728,
      "water_pixel_count": 988,
      "foam_pixel_count": 159.3529411764706,
      "total_buffer_pixels": 988
    },
    {
      "segment_id": "ns-seg-04002",
      "date": "2024-08-12",
      "swell_height_m": 0.78,
      "swell_period_s": 5.35,
      "swell_direction_deg": 184,
      "wave_height_m": 0.9,
      "cloud_pct": 0.02,
      "shadow_pct": 0.0,
      "snow_land_pct": 0.0,
      "valid_pct": 100.04,
      "quality_score": 100.0,
      "foam_fraction": 0.1467,
      "foam_extent_m": 72.2,
      "mean_nir": 369.3,
      "max_nir": 3144,
      "water_pixel_count": 984,
      "foam_pixel_count": 144.3529411764706,
      "total_buffer_pixels": 984
    },
    {
      "segment_id": "ns-seg-04002",
      "date": "2024-08-22",
      "swell_height_m": 0.66,
      "swell_period_s": 5.15,
      "swell_direction_deg": 173,
      "wave_height_m": 0.78,
      "cloud_pct": 12.64,
      "shadow_pct": 4.61,
      "snow_land_pct": 0.0,
      "valid_pct": 100.04,
      "quality_score": 94.5,
      "foam_fraction": 0.8745,
      "foam_extent_m": 32.8,
      "mean_nir": 2136.9,
      "max_nir": 3180,
      "water_pixel_count": 75,
      "foam_pixel_count": 65.5843137254902,
      "total_buffer_pixels": 75
    },
    {
      "segment_id": "ns-seg-04002",
      "date": "2024-08-25",
      "swell_height_m": 0.32,
      "swell_period_s": 4.0,
      "swell_direction_deg": 193,
      "wave_height_m": 0.44,
      "cloud_pct": 0.01,
      "shadow_pct": 0.0,
      "snow_land_pct": 0.0,
      "valid_pct": 100.04,
      "quality_score": 100.0,
      "foam_fraction": 0.1199,
      "foam_extent_m": 59.7,
      "mean_nir": 389.1,
      "max_nir": 3128,
      "water_pixel_count": 996,
      "foam_pixel_count": 119.43529411764706,
      "total_buffer_pixels": 996
    },
    {
      "segment_id": "ns-seg-04002",
      "date": "2024-08-30",
      "swell_height_m": 0.26,
      "swell_period_s": 9.35,
      "swell_direction_deg": 138,
      "wave_height_m": 0.34,
      "cloud_pct": 0.0,
      "shadow_pct": 0.0,
      "snow_land_pct": 0.0,
      "valid_pct": 100.04,
      "quality_score": 100.0,
      "foam_fraction": 0.2352,
      "foam_extent_m": 114.3,
      "mean_nir": 530.6,
      "max_nir": 3124,
      "water_pixel_count": 972,
      "foam_pixel_count": 228.64313725490197,
      "total_buffer_pixels": 972
    },
    {
      "segment_id": "ns-seg-04002",
      "date": "2024-09-04",
      "swell_height_m": 0.34,
      "swell_period_s": 9.15,
      "swell_direction_deg": 139,
      "wave_height_m": 0.5,
      "cloud_pct": 0.05,
      "shadow_pct": 0.0,
      "snow_land_pct": 0.0,
      "valid_pct": 100.04,
      "quality_score": 100.0,
      "foam_fraction": 0.1494,
      "foam_extent_m": 74.4,
      "mean_nir": 395.6,
      "max_nir": 2944,
      "water_pixel_count": 996,
      "foam_pixel_count": 148.79215686274512,
      "total_buffer_pixels": 996
    },
    {
      "segment_id": "ns-seg-04002",
      "date": "2024-09-11",
      "swell_height_m": 0.42,
      "swell_period_s": 4.1,
      "swell_direction_deg": 197,
      "wave_height_m": 0.62,
      "cloud_pct": 50.15,
      "shadow_pct": 15.41,
      "snow_land_pct": 0.0,
      "valid_pct": 100.04,
      "quality_score": 78.4,
      "foam_fraction": 0.1486,
      "foam_extent_m": 172.9,
      "mean_nir": 553.9,
      "max_nir": 4268,
      "water_pixel_count": 2327,
      "foam_pixel_count": 345.878431372549,
      "total_buffer_pixels": 2327
    },
    {
      "segment_id": "ns-seg-04002",
      "date": "2024-09-14",
      "swell_height_m": 0.38,
      "swell_period_s": 7.3,
      "swell_direction_deg": 125,
      "wave_height_m": 0.56,
      "cloud_pct": 0.05,
      "shadow_pct": 0.0,
      "snow_land_pct": 0.0,
      "valid_pct": 100.04,
      "quality_score": 100.0,
      "foam_fraction": 0.2367,
      "foam_extent_m": 117.4,
      "mean_nir": 610.4,
      "max_nir": 2784,
      "water_pixel_count": 992,
      "foam_pixel_count": 234.80392156862746,
      "total_buffer_pixels": 992
    },
    {
      "segment_id": "ns-seg-04002",
      "date": "2024-09-16",
      "swell_height_m": 0.38,
      "swell_period_s": 7.9,
      "swell_direction_deg": 132,
      "wave_height_m": 0.52,
      "cloud_pct": 0.0,
      "shadow_pct": 0.0,
      "snow_land_pct": 0.0,
      "valid_pct": 100.04,
      "quality_score": 100.0,
      "foam_fraction": 0.2671,
      "foam_extent_m": 133.6,
      "mean_nir": 563.9,
      "max_nir": 3228,
      "water_pixel_count": 1000,
      "foam_pixel_count": 267.1411764705882,
      "total_buffer_pixels": 1000
    },
    {
      "segment_id": "ns-seg-04002",
      "date": "2024-10-19",
      "swell_height_m": 0.54,
      "swell_period_s": 7.85,
      "swell_direction_deg": 176,
      "wave_height_m": 0.62,
      "cloud_pct": 0.0,
      "shadow_pct": 0.0,
      "snow_land_pct": 0.0,
      "valid_pct": 100.04,
      "quality_score": 100.0,
      "foam_fraction": 0.1586,
      "foam_extent_m": 80.9,
      "mean_nir": 346.8,
      "max_nir": 2798,
      "water_pixel_count": 1020,
      "foam_pixel_count": 161.79215686274512,
      "total_buffer_pixels": 1020
    },
    {
      "segment_id": "ns-seg-04002",
      "date": "2024-10-29",
      "swell_height_m": 0.32,
      "swell_period_s": 9.1,
      "swell_direction_deg": 117,
      "wave_height_m": 0.42,
      "cloud_pct": 0.06,
      "shadow_pct": 0.0,
      "snow_land_pct": 0.0,
      "valid_pct": 100.04,
      "quality_score": 100.0,
      "foam_fraction": 0.2789,
      "foam_extent_m": 140.6,
      "mean_nir": 534.4,
      "max_nir": 2558,
      "water_pixel_count": 1008,
      "foam_pixel_count": 281.1411764705882,
      "total_buffer_pixels": 1008
    },
    {
      "segment_id": "ns-seg-04002",
      "date": "2024-11-10",
      "swell_height_m": 0.14,
      "swell_period_s": 11.0,
      "swell_direction_deg": 162,
      "wave_height_m": 0.36,
      "cloud_pct": 0.01,
      "shadow_pct": 0.0,
      "snow_land_pct": 0.0,
      "valid_pct": 100.04,
      "quality_score": 100.0,
      "foam_fraction": 0.1914,
      "foam_extent_m": 98.4,
      "mean_nir": 377.2,
      "max_nir": 2558,
      "water_pixel_count": 1028,
      "foam_pixel_count": 196.79215686274512,
      "total_buffer_pixels": 1028
    },
    {
      "segment_id": "ns-seg-04002",
      "date": "2024-12-15",
      "swell_height_m": 0.56,
      "swell_period_s": 8.95,
      "swell_direction_deg": 147,
      "wave_height_m": 0.58,
      "cloud_pct": 3.16,
      "shadow_pct": 0.0,
      "snow_land_pct": 0.03,
      "valid_pct": 100.04,
      "quality_score": 98.7,
      "foam_fraction": 0.0323,
      "foam_extent_m": 8.7,
      "mean_nir": 194.8,
      "max_nir": 1914,
      "water_pixel_count": 536,
      "foam_pixel_count": 17.305882352941175,
      "total_buffer_pixels": 536
    },
    {
      "segment_id": "ns-seg-04002",
      "date": "2025-03-03",
      "swell_height_m": 0.6,
      "swell_period_s": 7.85,
      "swell_direction_deg": 207,
      "wave_height_m": 0.84,
      "cloud_pct": 2.24,
      "shadow_pct": 0.0,
      "snow_land_pct": 51.33,
      "valid_pct": 100.04,
      "quality_score": 88.8,
      "foam_fraction": 0.0552,
      "foam_extent_m": 18.0,
      "mean_nir": 180.0,
      "max_nir": 4104,
      "water_pixel_count": 652,
      "foam_pixel_count": 36,
      "total_buffer_pixels": 652
    },
    {
      "segment_id": "ns-seg-04002",
      "date": "2025-03-13",
      "swell_height_m": 1.04,
      "swell_period_s": 8.45,
      "swell_direction_deg": 158,
      "wave_height_m": 1.14,
      "cloud_pct": 0.9,
      "shadow_pct": 0.0,
      "snow_land_pct": 0.0,
      "valid_pct": 100.04,
      "quality_score": 99.6,
      "foam_fraction": 0.0346,
      "foam_extent_m": 12.5,
      "mean_nir": 172.2,
      "max_nir": 1554,
      "water_pixel_count": 722,
      "foam_pixel_count": 25,
      "total_buffer_pixels": 722
    },
    {
      "segment_id": "ns-seg-04002",
      "date": "2025-03-15",
      "swell_height_m": 0.8,
      "swell_period_s": 9.1,
      "swell_direction_deg": 104,
      "wave_height_m": 1.1,
      "cloud_pct": 26.22,
      "shadow_pct": 0.0,
      "snow_land_pct": 0.13,
      "valid_pct": 100.04,
      "quality_score": 89.5,
      "foam_fraction": 0.3164,
      "foam_extent_m": 160.7,
      "mean_nir": 617.0,
      "max_nir": 2798,
      "water_pixel_count": 1016,
      "foam_pixel_count": 321.4470588235294,
      "total_buffer_pixels": 1016
    },
    {
      "segment_id": "ns-seg-04002",
      "date": "2025-04-02",
      "swell_height_m": 1.44,
      "swell_period_s": 8.65,
      "swell_direction_deg": 179,
      "wave_height_m": 1.52,
      "cloud_pct": 3.55,
      "shadow_pct": 0.0,
      "snow_land_pct": 0.16,
      "valid_pct": 100.04,
      "quality_score": 98.6,
      "foam_fraction": 0.0142,
      "foam_extent_m": 2.6,
      "mean_nir": 216.1,
      "max_nir": 1730,
      "water_pixel_count": 361,
      "foam_pixel_count": 5.133333333333333,
      "total_buffer_pixels": 361
    },
    {
      "segment_id": "ns-seg-04002",
      "date": "2025-05-14",
      "swell_height_m": 0.26,
      "swell_period_s": 3.75,
      "swell_direction_deg": 198,
      "wave_height_m": 0.48,
      "cloud_pct": 0.08,
      "shadow_pct": 0.0,
      "snow_land_pct": 0.0,
      "valid_pct": 100.04,
      "quality_score": 100.0,
      "foam_fraction": 0.1802,
      "foam_extent_m": 88.7,
      "mean_nir": 612.1,
      "max_nir": 2518,
      "water_pixel_count": 984,
      "foam_pixel_count": 177.30196078431374,
      "total_buffer_pixels": 984
    },
    {
      "segment_id": "ns-seg-04002",
      "date": "2025-05-27",
      "swell_height_m": 0.3,
      "swell_period_s": 4.85,
      "swell_direction_deg": 207,
      "wave_height_m": 0.48,
      "cloud_pct": 0.05,
      "shadow_pct": 0.0,
      "snow_land_pct": 0.0,
      "valid_pct": 100.04,
      "quality_score": 100.0,
      "foam_fraction": 0.2433,
      "foam_extent_m": 116.8,
      "mean_nir": 695.0,
      "max_nir": 2880,
      "water_pixel_count": 960,
      "foam_pixel_count": 233.5607843137255,
      "total_buffer_pixels": 960
    },
    {
      "segment_id": "ns-seg-04002",
      "date": "2025-06-11",
      "swell_height_m": 0.98,
      "swell_period_s": 4.85,
      "swell_direction_deg": 173,
      "wave_height_m": 1.14,
      "cloud_pct": 0.05,
      "shadow_pct": 0.0,
      "snow_land_pct": 0.0,
      "valid_pct": 100.04,
      "quality_score": 100.0,
      "foam_fraction": 0.2454,
      "foam_extent_m": 117.3,
      "mean_nir": 700.1,
      "max_nir": 3428,
      "water_pixel_count": 956,
      "foam_pixel_count": 234.5607843137255,
      "total_buffer_pixels": 956
    },
    {
      "segment_id": "ns-seg-04002",
      "date": "2025-06-16",
      "swell_height_m": 0.52,
      "swell_period_s": 5.35,
      "swell_direction_deg": 168,
      "wave_height_m": 0.64,
      "cloud_pct": 0.5,
      "shadow_pct": 0.0,
      "snow_land_pct": 0.0,
      "valid_pct": 100.04,
      "quality_score": 99.8,
      "foam_fraction": 0.2757,
      "foam_extent_m": 111.4,
      "mean_nir": 828.9,
      "max_nir": 2780,
      "water_pixel_count": 808,
      "foam_pixel_count": 222.74901960784314,
      "total_buffer_pixels": 808
    },
    {
      "segment_id": "ns-seg-04002",
      "date": "2025-06-21",
      "swell_height_m": 0.82,
      "swell_period_s": 4.85,
      "swell_direction_deg": 203,
      "wave_height_m": 1.0,
      "cloud_pct": 0.1,
      "shadow_pct": 0.0,
      "snow_land_pct": 0.0,
      "valid_pct": 100.04,
      "quality_score": 100.0,
      "foam_fraction": 0.3465,
      "foam_extent_m": 163.5,
      "mean_nir": 874.2,
      "max_nir": 2818,
      "water_pixel_count": 944,
      "foam_pixel_count": 327.0509803921568,
      "total_buffer_pixels": 944
    },
    {
      "segment_id": "ns-seg-04002",
      "date": "2025-07-16",
      "swell_height_m": 0.52,
      "swell_period_s": 4.35,
      "swell_direction_deg": 181,
      "wave_height_m": 0.62,
      "cloud_pct": 0.0,
      "shadow_pct": 0.0,
      "snow_land_pct": 0.0,
      "valid_pct": 100.04,
      "quality_score": 100.0,
      "foam_fraction": 0.1271,
      "foam_extent_m": 61.3,
      "mean_nir": 509.1,
      "max_nir": 2602,
      "water_pixel_count": 964,
      "foam_pixel_count": 122.50980392156863,
      "total_buffer_pixels": 964
    },
    {
      "segment_id": "ns-seg-04002",
      "date": "2025-07-23",
      "swell_height_m": 0.36,
      "swell_period_s": 6.2,
      "swell_direction_deg": 165,
      "wave_height_m": 0.42,
      "cloud_pct": 0.04,
      "shadow_pct": 0.0,
      "snow_land_pct": 0.0,
      "valid_pct": 100.04,
      "quality_score": 100.0,
      "foam_fraction": 0.2246,
      "foam_extent_m": 106.0,
      "mean_nir": 575.6,
      "max_nir": 2728,
      "water_pixel_count": 944,
      "foam_pixel_count": 212.06274509803922,
      "total_buffer_pixels": 944
    },
    {
      "segment_id": "ns-seg-04002",
      "date": "2025-07-26",
      "swell_height_m": 0.42,
      "swell_period_s": 4.55,
      "swell_direction_deg": 195,
      "wave_height_m": 0.62,
      "cloud_pct": 0.0,
      "shadow_pct": 0.0,
      "snow_land_pct": 0.0,
      "valid_pct": 100.04,
      "quality_score": 100.0,
      "foam_fraction": 0.1493,
      "foam_extent_m": 71.7,
      "mean_nir": 623.8,
      "max_nir": 3020,
      "water_pixel_count": 960,
      "foam_pixel_count": 143.30196078431374,
      "total_buffer_pixels": 960
    },
    {
      "segment_id": "ns-seg-04002",
      "date": "2025-07-28",
      "swell_height_m": 0.26,
      "swell_period_s": 8.6,
      "swell_direction_deg": 139,
      "wave_height_m": 0.48,
      "cloud_pct": 14.89,
      "shadow_pct": 0.0,
      "snow_land_pct": 0.0,
      "valid_pct": 100.04,
      "quality_score": 94.0,
      "foam_fraction": 0.1043,
      "foam_extent_m": 43.7,
      "mean_nir": 273.6,
      "max_nir": 3412,
      "water_pixel_count": 837,
      "foam_pixel_count": 87.30588235294118,
      "total_buffer_pixels": 837
    },
    {
      "segment_id": "ns-seg-04002",
      "date": "2025-08-02",
      "swell_height_m": 0.8,
      "swell_period_s": 5.75,
      "swell_direction_deg": 109,
      "wave_height_m": 0.84,
      "cloud_pct": 0.11,
      "shadow_pct": 0.0,
      "snow_land_pct": 0.0,
      "valid_pct": 100.04,
      "quality_score": 100.0,
      "foam_fraction": 0.1849,
      "foam_extent_m": 88.0,
      "mean_nir": 485.4,
      "max_nir": 2834,
      "water_pixel_count": 952,
      "foam_pixel_count": 176.06274509803922,
      "total_buffer_pixels": 952
    },
    {
      "segment_id": "ns-seg-04002",
      "date": "2025-08-12",
      "swell_height_m": 0.74,
      "swell_period_s": 6.05,
      "swell_direction_deg": 131,
      "wave_height_m": 0.82,
      "cloud_pct": 0.04,
      "shadow_pct": 0.0,
      "snow_land_pct": 0.0,
      "valid_pct": 100.04,
      "quality_score": 100.0,
      "foam_fraction": 0.1521,
      "foam_extent_m": 75.7,
      "mean_nir": 328.5,
      "max_nir": 2964,
      "water_pixel_count": 996,
      "foam_pixel_count": 151.4470588235294,
      "total_buffer_pixels": 996
    },
    {
      "segment_id": "ns-seg-04002",
      "date": "2025-08-15",
      "swell_height_m": 0.5,
      "swell_period_s": 6.4,
      "swell_direction_deg": 146,
      "wave_height_m": 0.68,
      "cloud_pct": 0.03,
      "shadow_pct": 0.0,
      "snow_land_pct": 0.0,
      "valid_pct": 100.04,
      "quality_score": 100.0,
      "foam_fraction": 0.139,
      "foam_extent_m": 67.3,
      "mean_nir": 473.0,
      "max_nir": 2846,
      "water_pixel_count": 968,
      "foam_pixel_count": 134.50980392156862,
      "total_buffer_pixels": 968
    },
    {
      "segment_id": "ns-seg-04002",
      "date": "2025-08-17",
      "swell_height_m": 0.4,
      "swell_period_s": 5.05,
      "swell_direction_deg": 92,
      "wave_height_m": 0.68,
      "cloud_pct": 2.4,
      "shadow_pct": 0.0,
      "snow_land_pct": 0.0,
      "valid_pct": 100.04,
      "quality_score": 99.0,
      "foam_fraction": 0.1056,
      "foam_extent_m": 21.5,
      "mean_nir": 275.7,
      "max_nir": 2946,
      "water_pixel_count": 407,
      "foam_pixel_count": 42.99607843137255,
      "total_buffer_pixels": 407
    },
    {
      "segment_id": "ns-seg-04002",
      "date": "2025-09-01",
      "swell_height_m": 0.42,
      "swell_period_s": 5.75,
      "swell_direction_deg": 174,
      "wave_height_m": 0.52,
      "cloud_pct": 5.58,
      "shadow_pct": 1.52,
      "snow_land_pct": 0.0,
      "valid_pct": 100.04,
      "quality_score": 97.6,
      "foam_fraction": 0.1868,
      "foam_extent_m": 88.2,
      "mean_nir": 391.8,
      "max_nir": 2972,
      "water_pixel_count": 944,
      "foam_pixel_count": 176.30196078431374,
      "total_buffer_pixels": 944
    },
    {
      "segment_id": "ns-seg-04002",
      "date": "2025-09-04",
      "swell_height_m": 0.62,
      "swell_period_s": 6.5,
      "swell_direction_deg": 111,
      "wave_height_m": 0.76,
      "cloud_pct": 0.02,
      "shadow_pct": 0.0,
      "snow_land_pct": 0.0,
      "valid_pct": 100.04,
      "quality_score": 100.0,
      "foam_fraction": 0.2225,
      "foam_extent_m": 104.2,
      "mean_nir": 482.7,
      "max_nir": 2340,
      "water_pixel_count": 936,
      "foam_pixel_count": 208.30196078431374,
      "total_buffer_pixels": 936
    },
    {
      "segment_id": "ns-seg-04002",
      "date": "2025-09-14",
      "swell_height_m": 0.38,
      "swell_period_s": 9.45,
      "swell_direction_deg": 134,
      "wave_height_m": 0.5,
      "cloud_pct": 82.12,
      "shadow_pct": 2.1,
      "snow_land_pct": 0.0,
      "valid_pct": 100.04,
      "quality_score": 66.9,
      "foam_fraction": 0.3174,
      "foam_extent_m": 163.0,
      "mean_nir": 677.7,
      "max_nir": 2330,
      "water_pixel_count": 1027,
      "foam_pixel_count": 326.00784313725495,
      "total_buffer_pixels": 1027
    },
    {
      "segment_id": "ns-seg-04002",
      "date": "2025-09-16",
      "swell_height_m": 0.48,
      "swell_period_s": 6.25,
      "swell_direction_deg": 116,
      "wave_height_m": 0.52,
      "cloud_pct": 0.02,
      "shadow_pct": 0.0,
      "snow_land_pct": 0.0,
      "valid_pct": 100.04,
      "quality_score": 100.0,
      "foam_fraction": 0.2243,
      "foam_extent_m": 107.7,
      "mean_nir": 494.7,
      "max_nir": 2800,
      "water_pixel_count": 960,
      "foam_pixel_count": 215.30196078431374,
      "total_buffer_pixels": 960
    },
    {
      "segment_id": "ns-seg-04002",
      "date": "2025-09-21",
      "swell_height_m": 0.5,
      "swell_period_s": 11.05,
      "swell_direction_deg": 152,
      "wave_height_m": 0.58,
      "cloud_pct": 0.06,
      "shadow_pct": 0.0,
      "snow_land_pct": 0.0,
      "valid_pct": 100.04,
      "quality_score": 100.0,
      "foam_fraction": 0.1972,
      "foam_extent_m": 94.7,
      "mean_nir": 412.6,
      "max_nir": 2820,
      "water_pixel_count": 960,
      "foam_pixel_count": 189.30196078431374,
      "total_buffer_pixels": 960
    },
    {
      "segment_id": "ns-seg-04002",
      "date": "2025-09-29",
      "swell_height_m": 0.34,
      "swell_period_s": 5.55,
      "swell_direction_deg": 181,
      "wave_height_m": 0.58,
      "cloud_pct": 0.0,
      "shadow_pct": 0.0,
      "snow_land_pct": 0.0,
      "valid_pct": 100.04,
      "quality_score": 100.0,
      "foam_fraction": 0.1271,
      "foam_extent_m": 61.3,
      "mean_nir": 263.8,
      "max_nir": 2384,
      "water_pixel_count": 964,
      "foam_pixel_count": 122.50980392156863,
      "total_buffer_pixels": 964
    },
    {
      "segment_id": "ns-seg-04002",
      "date": "2025-10-04",
      "swell_height_m": 0.46,
      "swell_period_s": 9.95,
      "swell_direction_deg": 141,
      "wave_height_m": 0.72,
      "cloud_pct": 0.0,
      "shadow_pct": 0.0,
      "snow_land_pct": 0.0,
      "valid_pct": 100.04,
      "quality_score": 100.0,
      "foam_fraction": 0.2563,
      "foam_extent_m": 122.0,
      "mean_nir": 471.0,
      "max_nir": 2214,
      "water_pixel_count": 952,
      "foam_pixel_count": 244.03529411764708,
      "total_buffer_pixels": 952
    },
    {
      "segment_id": "ns-seg-04002",
      "date": "2025-10-24",
      "swell_height_m": 0.62,
      "swell_period_s": 8.2,
      "swell_direction_deg": 140,
      "wave_height_m": 0.98,
      "cloud_pct": 0.0,
      "shadow_pct": 0.0,
      "snow_land_pct": 0.04,
      "valid_pct": 100.04,
      "quality_score": 100.0,
      "foam_fraction": 0.1596,
      "foam_extent_m": 78.2,
      "mean_nir": 353.0,
      "max_nir": 2620,
      "water_pixel_count": 980,
      "foam_pixel_count": 156.3607843137255,
      "total_buffer_pixels": 980
    },
    {
      "segment_id": "ns-seg-04002",
      "date": "2025-11-03",
      "swell_height_m": 0.48,
      "swell_period_s": 5.45,
      "swell_direction_deg": 198,
      "wave_height_m": 0.6,
      "cloud_pct": 0.0,
      "shadow_pct": 0.0,
      "snow_land_pct": 0.0,
      "valid_pct": 100.04,
      "quality_score": 100.0,
      "foam_fraction": 0.3861,
      "foam_extent_m": 185.3,
      "mean_nir": 688.5,
      "max_nir": 2318,
      "water_pixel_count": 960,
      "foam_pixel_count": 370.63529411764705,
      "total_buffer_pixels": 960
    },
    {
      "segment_id": "ns-seg-04002",
      "date": "2025-11-05",
      "swell_height_m": 0.42,
      "swell_period_s": 5.55,
      "swell_direction_deg": 231,
      "wave_height_m": 0.9,
      "cloud_pct": 0.06,
      "shadow_pct": 0.0,
      "snow_land_pct": 0.0,
      "valid_pct": 100.04,
      "quality_score": 100.0,
      "foam_fraction": 0.3228,
      "foam_extent_m": 157.5,
      "mean_nir": 634.8,
      "max_nir": 2570,
      "water_pixel_count": 976,
      "foam_pixel_count": 315.0627450980392,
      "total_buffer_pixels": 976
    },
    {
      "segment_id": "ns-seg-04002",
      "date": "2025-11-23",
      "swell_height_m": 0.4,
      "swell_period_s": 6.1,
      "swell_direction_deg": 160,
      "wave_height_m": 0.66,
      "cloud_pct": 0.0,
      "shadow_pct": 0.0,
      "snow_land_pct": 0.0,
      "valid_pct": 100.04,
      "quality_score": 100.0,
      "foam_fraction": 0.188,
      "foam_extent_m": 98.3,
      "mean_nir": 394.3,
      "max_nir": 2800,
      "water_pixel_count": 1046,
      "foam_pixel_count": 196.6392156862745,
      "total_buffer_pixels": 1046
    },
    {
      "segment_id": "ns-seg-04002",
      "date": "2025-12-05",
      "swell_height_m": 0.64,
      "swell_period_s": 9.6,
      "swell_direction_deg": 204,
      "wave_height_m": 1.06,
      "cloud_pct": 1.72,
      "shadow_pct": 0.91,
      "snow_land_pct": 0.0,
      "valid_pct": 100.04,
      "quality_score": 99.2,
      "foam_fraction": 0.2137,
      "foam_extent_m": 90.5,
      "mean_nir": 620.8,
      "max_nir": 4624,
      "water_pixel_count": 847,
      "foam_pixel_count": 181.01176470588237,
      "total_buffer_pixels": 847
    },
    {
      "segment_id": "ns-seg-04002",
      "date": "2025-12-18",
      "swell_height_m": 0.92,
      "swell_period_s": 7.5,
      "swell_direction_deg": 196,
      "wave_height_m": 1.04,
      "cloud_pct": 0.05,
      "shadow_pct": 0.0,
      "snow_land_pct": 0.28,
      "valid_pct": 100.04,
      "quality_score": 99.9,
      "foam_fraction": 0.3321,
      "foam_extent_m": 164.4,
      "mean_nir": 699.1,
      "max_nir": 2902,
      "water_pixel_count": 990,
      "foam_pixel_count": 328.78823529411767,
      "total_buffer_pixels": 990
    },
    {
      "segment_id": "ns-seg-04002",
      "date": "2025-12-23",
      "swell_height_m": 0.32,
      "swell_period_s": 9.7,
      "swell_direction_deg": 134,
      "wave_height_m": 0.64,
      "cloud_pct": 0.94,
      "shadow_pct": 0.0,
      "snow_land_pct": 0.0,
      "valid_pct": 100.04,
      "quality_score": 99.6,
      "foam_fraction": 0.0146,
      "foam_extent_m": 5.5,
      "mean_nir": 162.5,
      "max_nir": 2728,
      "water_pixel_count": 751,
      "foam_pixel_count": 11,
      "total_buffer_pixels": 751
    },
    {
      "segment_id": "ns-seg-04002",
      "date": "2026-02-13",
      "swell_height_m": 0.74,
      "swell_period_s": 8.7,
      "swell_direction_deg": 178,
      "wave_height_m": 0.84,
      "cloud_pct": 6.61,
      "shadow_pct": 0.0,
      "snow_land_pct": 77.44,
      "valid_pct": 100.04,
      "quality_score": 81.9,
      "foam_fraction": 0.1927,
      "foam_extent_m": 43.8,
      "mean_nir": 503.3,
      "max_nir": 2155,
      "water_pixel_count": 455,
      "foam_pixel_count": 87.65882352941176,
      "total_buffer_pixels": 455
    },
    {
      "segment_id": "ns-seg-04002",
      "date": "2026-02-28",
      "swell_height_m": 1.06,
      "swell_period_s": 7.4,
      "swell_direction_deg": 175,
      "wave_height_m": 1.06,
      "cloud_pct": 0.0,
      "shadow_pct": 0.0,
      "snow_land_pct": 87.26,
      "valid_pct": 100.04,
      "quality_score": 82.5,
      "foam_fraction": 0.3883,
      "foam_extent_m": 191.0,
      "mean_nir": 908.1,
      "max_nir": 6309,
      "water_pixel_count": 984,
      "foam_pixel_count": 382.0627450980392,
      "total_buffer_pixels": 984
    },
    {
      "segment_id": "ns-seg-04002",
      "date": "2026-03-03",
      "swell_height_m": 0.46,
      "swell_period_s": 8.25,
      "swell_direction_deg": 150,
      "wave_height_m": 0.64,
      "cloud_pct": 0.0,
      "shadow_pct": 0.0,
      "snow_land_pct": 85.98,
      "valid_pct": 100.04,
      "quality_score": 82.8,
      "foam_fraction": 0.3377,
      "foam_extent_m": 167.4,
      "mean_nir": 861.5,
      "max_nir": 7402,
      "water_pixel_count": 991,
      "foam_pixel_count": 334.70980392156866,
      "total_buffer_pixels": 991
    },
    {
      "segment_id": "ns-seg-04002",
      "date": "2026-03-10",
      "swell_height_m": 0.86,
      "swell_period_s": 4.6,
      "swell_direction_deg": 186,
      "wave_height_m": 0.96,
      "cloud_pct": 0.01,
      "shadow_pct": 0.0,
      "snow_land_pct": 71.29,
      "valid_pct": 100.04,
      "quality_score": 85.7,
      "foam_fraction": 0.3146,
      "foam_extent_m": 160.2,
      "mean_nir": 626.8,
      "max_nir": 5000,
      "water_pixel_count": 1018,
      "foam_pixel_count": 320.30980392156863,
      "total_buffer_pixels": 1018
    },
    {
      "segment_id": "ns-seg-04002",
      "date": "2026-03-18",
      "swell_height_m": 2.1,
      "swell_period_s": 9.0,
      "swell_direction_deg": 175,
      "wave_height_m": 2.2,
      "cloud_pct": 7.57,
      "shadow_pct": 0.0,
      "snow_land_pct": 4.92,
      "valid_pct": 100.04,
      "quality_score": 96.0,
      "foam_fraction": 0.0269,
      "foam_extent_m": 3.1,
      "mean_nir": 182.8,
      "max_nir": 1909,
      "water_pixel_count": 233,
      "foam_pixel_count": 6.258823529411765,
      "total_buffer_pixels": 233
    }
  ]
}
