{
  "name": "Atlas Section atlas-2157",
  "slug": "atlas-2157",
  "region": "nova-scotia",
  "bbox": [
    -60.045288,
    46.209707,
    -60.0294,
    46.22991
  ],
  "point": {
    "lat": 46.21836,
    "lon": -60.03772
  },
  "date_range": {
    "start": "2021-10-01"
  },
  "export": {
    "drive_folder": "wavescout_atlas"
  },
  "atlas_metadata": {
    "mean_score": 47.4,
    "max_score": 80.0,
    "segment_count": 6,
    "segment_ids": [
      "ns-seg-16255",
      "ns-seg-16256",
      "ns-seg-16257",
      "ns-seg-16258",
      "ns-seg-16528",
      "ns-seg-16529"
    ],
    "coastline_length_m": 6504.0
  }
}
